Workbook

Sheet Student Details
B2: Name | C2: Shreya Khubber
B3: ID | C3: 2020A8PS1807P
B4: PS Station: | C4: Morningstar

Sheet Horizontal Analysis - Allcargo
A1: Horizontal Analysis of the Income Statement
A3: In Millions of INR except Per Share | B3: FY 2018 | C3: FY 2019 | D3: FY 2020 | E3: FY 2021 | F3: FY 2022 | G3: FY 2023 | J3: In Millions of INR except Per Share | K3: FY 2019 | L3: FY 2020 | M3: FY 2021 | N3: FY 2022 | O3: FY 2023
A4: 12 Months Ending | B4: 03/31/2018 | C4: 03/31/2019 | D4: 03/31/2020 | E4: 03/31/2021 | F4: 03/31/2022 | G4: 03/31/2023 | J4: 12 Months Ending | K4: 03/31/2019 | L4: 03/31/2020 | M4: 03/31/2021 | N4: 03/31/2022 | O4: 03/31/2023
A5: Revenue | B5: 60335.4 | C5: 68814.1 | D5: 73387 | E5: 104884.5 | F5: 190620.7 | G5: 180507.7 | J5: Revenue | K5: =IFERROR((C5/$C5)*100, "") -> 100 | L5: =IFERROR((D5/$C5)*100, "") -> 106.6453 | M5: =IFERROR((E5/$C5)*100, "") -> 152.41716 | N5: =IFERROR((F5/$C5)*100, "") -> 277.0082 | O5: =IFERROR((G5/$C5)*100, "") -> 262.31208
A6: + Sales & Services Revenue | B6: 60335.4 | C6: 68814.1 | D6: 73387 | E6: 104884.5 | F6: 190620.7 | G6: 180507.7 | J6: + Sales & Services Revenue | K6: =IFERROR((C6/$C6)*100, "") -> 100 | L6: =IFERROR((D6/$C6)*100, "") -> 106.6453 | M6: =IFERROR((E6/$C6)*100, "") -> 152.41716 | N6: =IFERROR((F6/$C6)*100, "") -> 277.0082 | O6: =IFERROR((G6/$C6)*100, "") -> 262.31208
A7: + Other Operating Income | B7: 156.5 | C7: 134.5 | D7: 75.4 | E7: 96.5 | F7: 0 | G7: 0 | J7: + Other Operating Income | K7: =IFERROR((C7/$C7)*100, "") -> 100 | L7: =IFERROR((D7/$C7)*100, "") -> 56.05948 | M7: =IFERROR((E7/$C7)*100, "") -> 71.747212 | N7: =IFERROR((F7/$C7)*100, "") -> 0 | O7: =IFERROR((G7/$C7)*100, "") -> 0
A8: - Operating Expenses | B8: 58311.2 | C8: 66022.8 | D8: 70689.2 | E8: 100706.6 | F8: 179578.1 | G8: 171319.9 | J8: - Operating Expenses | K8: =IFERROR((C8/$C8)*100, "") -> 100 | L8: =IFERROR((D8/$C8)*100, "") -> 107.06786 | M8: =IFERROR((E8/$C8)*100, "") -> 152.53306 | N8: =IFERROR((F8/$C8)*100, "") -> 271.99407 | O8: =IFERROR((G8/$C8)*100, "") -> 259.48597
A9: + Selling, General & Admin | B9: — | C9: — | D9: — | E9: — | F9: — | G9: — | J9: + Selling, General & Admin | K9: =IFERROR((C9/$C9)*100, "") | L9: =IFERROR((D9/$C9)*100, "") | M9: =IFERROR((E9/$C9)*100, "") | N9: =IFERROR((F9/$C9)*100, "") | O9: =IFERROR((G9/$C9)*100, "")
A10: + Selling & Marketing | B10: 282.3 | C10: 248.1 | D10: 264.4 | E10: 117.2 | F10: 0 | G10: 47.8 | J10: + Selling & Marketing | K10: =IFERROR((C10/$C10)*100, "") -> 100 | L10: =IFERROR((D10/$C10)*100, "") -> 106.56993 | M10: =IFERROR((E10/$C10)*100, "") -> 47.239017 | N10: =IFERROR((F10/$C10)*100, "") -> 0 | O10: =IFERROR((G10/$C10)*100, "") -> 19.266425
A11: + Research & Development | B11: 0 | C11: 0 | D11: 0 | E11: 0 | F11: — | G11: — | J11: + Research & Development | K11: =IFERROR((C11/$C11)*100, "") | L11: =IFERROR((D11/$C11)*100, "") | M11: =IFERROR((E11/$C11)*100, "") | N11: =IFERROR((F11/$C11)*100, "") | O11: =IFERROR((G11/$C11)*100, "")
A12: + Depreciation & Amortization | B12: 1590.6 | C12: 1559.3 | D12: 2316 | E12: 3060.9 | F12: 2375.7 | G12: 2780.1 | J12: + Depreciation & Amortization | K12: =IFERROR((C12/$C12)*100, "") -> 100 | L12: =IFERROR((D12/$C12)*100, "") -> 148.52819 | M12: =IFERROR((E12/$C12)*100, "") -> 196.29962 | N12: =IFERROR((F12/$C12)*100, "") -> 152.35683 | O12: =IFERROR((G12/$C12)*100, "") -> 178.29154
A13: + Prov For Doubtful Accts | B13: 298.1 | C13: -108.8 | D13: 161.8 | E13: 318.4 | F13: — | G13: — | J13: + Prov For Doubtful Accts | K13: =IFERROR((C13/$C13)*100, "") -> 100 | L13: =IFERROR((D13/$C13)*100, "") -> -148.71324 | M13: =IFERROR((E13/$C13)*100, "") -> -292.64706 | N13: =IFERROR((F13/$C13)*100, "") | O13: =IFERROR((G13/$C13)*100, "")
A14: + Other Operating Expense | B14: 56140.2 | C14: 64324.2 | D14: 67947 | E14: 97210.1 | F14: 177202.4 | G14: 168492 | J14: + Other Operating Expense | K14: =IFERROR((C14/$C14)*100, "") -> 100 | L14: =IFERROR((D14/$C14)*100, "") -> 105.63209 | M14: =IFERROR((E14/$C14)*100, "") -> 151.12524 | N14: =IFERROR((F14/$C14)*100, "") -> 275.48326 | O14: =IFERROR((G14/$C14)*100, "") -> 261.94185
A15: Operating Income (Loss) | B15: 2180.7 | C15: 2925.8 | D15: 2773.2 | E15: 4274.4 | F15: 11042.6 | G15: 9187.8 | J15: Operating Income (Loss) | K15: =IFERROR((C15/$C15)*100, "") -> 100 | L15: =IFERROR((D15/$C15)*100, "") -> 94.784332 | M15: =IFERROR((E15/$C15)*100, "") -> 146.09338 | N15: =IFERROR((F15/$C15)*100, "") -> 377.42156 | O15: =IFERROR((G15/$C15)*100, "") -> 314.02693
A16: - Non-Operating (Income) Loss | B16: 60.3 | C16: 99.9 | D16: -151.1 | E16: 2788.1 | F16: -143.2 | G16: -121.3 | J16: - Non-Operating (Income) Loss | K16: =IFERROR((C16/$C16)*100, "") -> 100 | L16: =IFERROR((D16/$C16)*100, "") -> -151.25125 | M16: =IFERROR((E16/$C16)*100, "") -> 2790.8909 | N16: =IFERROR((F16/$C16)*100, "") -> -143.34334 | O16: =IFERROR((G16/$C16)*100, "") -> -121.42142
A17: + Interest Expense, Net | B17: -20.2 | C17: -41.9 | D17: 3.3 | E17: 877 | F17: 162.3 | G17: -29.2 | J17: + Interest Expense, Net | K17: =IFERROR((C17/$C17)*100, "") -> 100 | L17: =IFERROR((D17/$C17)*100, "") -> -7.875895 | M17: =IFERROR((E17/$C17)*100, "") -> -2093.0788 | N17: =IFERROR((F17/$C17)*100, "") -> -387.35084 | O17: =IFERROR((G17/$C17)*100, "") -> 69.689737
A18: + Interest Expense | B18: 6 | C18: 2.5 | D18: 3.3 | E18: 980.9 | F18: 327.8 | G18: 243.7 | J18: + Interest Expense | K18: =IFERROR((C18/$C18)*100, "") -> 100 | L18: =IFERROR((D18/$C18)*100, "") -> 132 | M18: =IFERROR((E18/$C18)*100, "") -> 39236 | N18: =IFERROR((F18/$C18)*100, "") -> 13112 | O18: =IFERROR((G18/$C18)*100, "") -> 9748
A19: - Interest Income | B19: 26.2 | C19: 44.4 | D19: 0 | E19: 103.9 | F19: 165.5 | G19: 272.9 | J19: - Interest Income | K19: =IFERROR((C19/$C19)*100, "") -> 100 | L19: =IFERROR((D19/$C19)*100, "") -> 0 | M19: =IFERROR((E19/$C19)*100, "") -> 234.00901 | N19: =IFERROR((F19/$C19)*100, "") -> 372.74775 | O19: =IFERROR((G19/$C19)*100, "") -> 614.63964
A20: + Other Investment (Inc) Loss | B20: — | C20: — | D20: — | E20: -8 | F20: -1.9 | G20: -16 | J20: + Other Investment (Inc) Loss | K20: =IFERROR((C20/$C20)*100, "") | L20: =IFERROR((D20/$C20)*100, "") | M20: =IFERROR((E20/$C20)*100, "") | N20: =IFERROR((F20/$C20)*100, "") | O20: =IFERROR((G20/$C20)*100, "")
A21: + Foreign Exch (Gain) Loss | B21: -2.2 | C21: -13.7 | D21: 0 | E21: 0 | F21: 0 | G21: -47.7 | J21: + Foreign Exch (Gain) Loss | K21: =IFERROR((C21/$C21)*100, "") -> 100 | L21: =IFERROR((D21/$C21)*100, "") -> 0 | M21: =IFERROR((E21/$C21)*100, "") -> 0 | N21: =IFERROR((F21/$C21)*100, "") -> 0 | O21: =IFERROR((G21/$C21)*100, "") -> 348.17518
A22: + (Income) Loss from Affiliates | B22: -48 | C22: -52.1 | D22: -60.7 | E22: -170 | F22: -812 | G22: -174.4 | J22: + (Income) Loss from Affiliates | K22: =IFERROR((C22/$C22)*100, "") -> 100 | L22: =IFERROR((D22/$C22)*100, "") -> 116.50672 | M22: =IFERROR((E22/$C22)*100, "") -> 326.29559 | N22: =IFERROR((F22/$C22)*100, "") -> 1558.5413 | O22: =IFERROR((G22/$C22)*100, "") -> 334.74088
A23: + Other Non-Op (Income) Loss | B23: 130.7 | C23: 207.6 | D23: -93.7 | E23: 2089.1 | F23: 508.4 | G23: 146 | J23: + Other Non-Op (Income) Loss | K23: =IFERROR((C23/$C23)*100, "") -> 100 | L23: =IFERROR((D23/$C23)*100, "") -> -45.134875 | M23: =IFERROR((E23/$C23)*100, "") -> 1006.3102 | N23: =IFERROR((F23/$C23)*100, "") -> 244.89403 | O23: =IFERROR((G23/$C23)*100, "") -> 70.327553
A24: Pretax Income (Loss), Adjusted | B24: 2120.4 | C24: 2825.9 | D24: 2924.3 | E24: 1486.3 | F24: 11185.8 | G24: 9309.1 | J24: Pretax Income (Loss), Adjusted | K24: =IFERROR((C24/$C24)*100, "") -> 100 | L24: =IFERROR((D24/$C24)*100, "") -> 103.48208 | M24: =IFERROR((E24/$C24)*100, "") -> 52.595633 | N24: =IFERROR((F24/$C24)*100, "") -> 395.83142 | O24: =IFERROR((G24/$C24)*100, "") -> 329.42072
A25: - Abnormal Losses (Gains) | B25: -131.8 | C25: -194.9 | D25: -130.1 | E25: -104.5 | F25: 375.1 | G25: 355.7 | J25: - Abnormal Losses (Gains) | K25: =IFERROR((C25/$C25)*100, "") -> 100 | L25: =IFERROR((D25/$C25)*100, "") -> 66.752181 | M25: =IFERROR((E25/$C25)*100, "") -> 53.61724 | N25: =IFERROR((F25/$C25)*100, "") -> -192.45767 | O25: =IFERROR((G25/$C25)*100, "") -> -182.50385
A26: + Disposal of Assets | B26: -149.3 | C26: -127.1 | D26: 31.6 | E26: -90.6 | F26: 14.4 | G26: 3.2 | J26: + Disposal of Assets | K26: =IFERROR((C26/$C26)*100, "") -> 100 | L26: =IFERROR((D26/$C26)*100, "") -> -24.862313 | M26: =IFERROR((E26/$C26)*100, "") -> 71.282455 | N26: =IFERROR((F26/$C26)*100, "") -> -11.329662 | O26: =IFERROR((G26/$C26)*100, "") -> -2.5177026
A27: + Asset Write-Down | B27: — | C27: — | D27: — | E27: — | F27: 555.8 | G27: 702.8 | J27: + Asset Write-Down | K27: =IFERROR((C27/$C27)*100, "") | L27: =IFERROR((D27/$C27)*100, "") | M27: =IFERROR((E27/$C27)*100, "") | N27: =IFERROR((F27/$C27)*100, "") | O27: =IFERROR((G27/$C27)*100, "")
A28: + Impairment of Goodwill | B28: 68.6 | C28: — | D28: — | E28: — | F28: — | G28: — | J28: + Impairment of Goodwill | K28: =IFERROR((C28/$C28)*100, "") | L28: =IFERROR((D28/$C28)*100, "") | M28: =IFERROR((E28/$C28)*100, "") | N28: =IFERROR((F28/$C28)*100, "") | O28: =IFERROR((G28/$C28)*100, "")
A29: + Gain/Loss on Sale/Acquisition of Business | B29: — | C29: — | D29: -125.8 | E29: — | F29: -185.1 | G29: -278.7 | J29: + Gain/Loss on Sale/Acquisition of Business | K29: =IFERROR((C29/$C29)*100, "") | L29: =IFERROR((D29/$C29)*100, "") | M29: =IFERROR((E29/$C29)*100, "") | N29: =IFERROR((F29/$C29)*100, "") | O29: =IFERROR((G29/$C29)*100, "")
A30: + Sale of Investments | B30: -51.1 | C30: -67.8 | D30: -35.9 | E30: -13.9 | F30: -6.7 | G30: -50.2 | J30: + Sale of Investments | K30: =IFERROR((C30/$C30)*100, "") -> 100 | L30: =IFERROR((D30/$C30)*100, "") -> 52.949853 | M30: =IFERROR((E30/$C30)*100, "") -> 20.501475 | N30: =IFERROR((F30/$C30)*100, "") -> 9.8820059 | O30: =IFERROR((G30/$C30)*100, "") -> 74.041298
A31: + Unrealized Investments | B31: — | C31: — | D31: — | E31: — | F31: -3.3 | G31: -21.4 | J31: + Unrealized Investments | K31: =IFERROR((C31/$C31)*100, "") | L31: =IFERROR((D31/$C31)*100, "") | M31: =IFERROR((E31/$C31)*100, "") | N31: =IFERROR((F31/$C31)*100, "") | O31: =IFERROR((G31/$C31)*100, "")
A32: + Other Abnormal Items | B32: — | C32: — | D32: — | E32: — | F32: — | G32: — | J32: + Other Abnormal Items | K32: =IFERROR((C32/$C32)*100, "") | L32: =IFERROR((D32/$C32)*100, "") | M32: =IFERROR((E32/$C32)*100, "") | N32: =IFERROR((F32/$C32)*100, "") | O32: =IFERROR((G32/$C32)*100, "")
A33: Pretax Income (Loss), GAAP | B33: 2252.2 | C33: 3020.8 | D33: 3054.4 | E33: 1590.8 | F33: 10810.7 | G33: 8953.4 | J33: Pretax Income (Loss), GAAP | K33: =IFERROR((C33/$C33)*100, "") -> 100 | L33: =IFERROR((D33/$C33)*100, "") -> 101.11229 | M33: =IFERROR((E33/$C33)*100, "") -> 52.661547 | N33: =IFERROR((F33/$C33)*100, "") -> 357.8754 | O33: =IFERROR((G33/$C33)*100, "") -> 296.39168
A34: - Income Tax Expense (Benefit) | B34: 512.6 | C34: 542.4 | D34: 711 | E34: 639.7 | F34: 2570.2 | G34: 2421.3 | J34: - Income Tax Expense (Benefit) | K34: =IFERROR((C34/$C34)*100, "") -> 100 | L34: =IFERROR((D34/$C34)*100, "") -> 131.08407 | M34: =IFERROR((E34/$C34)*100, "") -> 117.93879 | N34: =IFERROR((F34/$C34)*100, "") -> 473.85693 | O34: =IFERROR((G34/$C34)*100, "") -> 446.40487
A35: + Current Income Tax | B35: 602.8 | C35: 925.3 | D35: 1345 | E35: 1267.7 | F35: 2803.3 | G35: 2508.2 | J35: + Current Income Tax | K35: =IFERROR((C35/$C35)*100, "") -> 100 | L35: =IFERROR((D35/$C35)*100, "") -> 145.35826 | M35: =IFERROR((E35/$C35)*100, "") -> 137.00421 | N35: =IFERROR((F35/$C35)*100, "") -> 302.9612 | O35: =IFERROR((G35/$C35)*100, "") -> 271.06884
A36: + Deferred Income Tax | B36: -90.2 | C36: -382.9 | D36: -634 | E36: -628 | F36: -233.1 | G36: -86.9 | J36: + Deferred Income Tax | K36: =IFERROR((C36/$C36)*100, "") -> 100 | L36: =IFERROR((D36/$C36)*100, "") -> 165.57848 | M36: =IFERROR((E36/$C36)*100, "") -> 164.01149 | N36: =IFERROR((F36/$C36)*100, "") -> 60.877514 | O36: =IFERROR((G36/$C36)*100, "") -> 22.695221
A37: + Tax Allowance/Credit | B37: — | C37: — | D37: — | E37: — | F37: — | G37: — | J37: + Tax Allowance/Credit | K37: =IFERROR((C37/$C37)*100, "") | L37: =IFERROR((D37/$C37)*100, "") | M37: =IFERROR((E37/$C37)*100, "") | N37: =IFERROR((F37/$C37)*100, "") | O37: =IFERROR((G37/$C37)*100, "")
A38: - (Income) Loss from Affiliates | B38: — | C38: — | D38: — | E38: — | F38: — | G38: — | J38: - (Income) Loss from Affiliates | K38: =IFERROR((C38/$C38)*100, "") | L38: =IFERROR((D38/$C38)*100, "") | M38: =IFERROR((E38/$C38)*100, "") | N38: =IFERROR((F38/$C38)*100, "") | O38: =IFERROR((G38/$C38)*100, "")
A39: Income (Loss) from Cont Ops | B39: 1739.6 | C39: 2478.4 | D39: 2343.4 | E39: 951.1 | F39: 8240.5 | G39: 6532.1 | J39: Income (Loss) from Cont Ops | K39: =IFERROR((C39/$C39)*100, "") -> 100 | L39: =IFERROR((D39/$C39)*100, "") -> 94.552937 | M39: =IFERROR((E39/$C39)*100, "") -> 38.375565 | N39: =IFERROR((F39/$C39)*100, "") -> 332.49274 | O39: =IFERROR((G39/$C39)*100, "") -> 263.56117
A40: - Net Extraordinary Losses (Gains) | B40: 0 | C40: 0 | D40: 0 | E40: 0 | F40: -1405.4 | G40: 0 | J40: - Net Extraordinary Losses (Gains) | K40: =IFERROR((C40/$C40)*100, "") | L40: =IFERROR((D40/$C40)*100, "") | M40: =IFERROR((E40/$C40)*100, "") | N40: =IFERROR((F40/$C40)*100, "") | O40: =IFERROR((G40/$C40)*100, "")
A41: + Discontinued Operations | B41: 0 | C41: 0 | D41: 0 | E41: 0 | F41: -1405.4 | G41: 0 | J41: + Discontinued Operations | K41: =IFERROR((C41/$C41)*100, "") | L41: =IFERROR((D41/$C41)*100, "") | M41: =IFERROR((E41/$C41)*100, "") | N41: =IFERROR((F41/$C41)*100, "") | O41: =IFERROR((G41/$C41)*100, "")
A42: + XO & Accounting Changes | B42: 0 | C42: 0 | D42: 0 | E42: 0 | F42: 0 | G42: 0 | J42: + XO & Accounting Changes | K42: =IFERROR((C42/$C42)*100, "") | L42: =IFERROR((D42/$C42)*100, "") | M42: =IFERROR((E42/$C42)*100, "") | N42: =IFERROR((F42/$C42)*100, "") | O42: =IFERROR((G42/$C42)*100, "")
A43: Income (Loss) Incl. MI | B43: 1739.6 | C43: 2478.4 | D43: 2343.4 | E43: 951.1 | F43: 9645.9 | G43: 6532.1 | J43: Income (Loss) Incl. MI | K43: =IFERROR((C43/$C43)*100, "") -> 100 | L43: =IFERROR((D43/$C43)*100, "") -> 94.552937 | M43: =IFERROR((E43/$C43)*100, "") -> 38.375565 | N43: =IFERROR((F43/$C43)*100, "") -> 389.19868 | O43: =IFERROR((G43/$C43)*100, "") -> 263.56117
A44: - Minority Interest | B44: 26.1 | C44: 58.8 | D44: 113.4 | E44: -777.9 | F44: 388.7 | G44: 236.2 | J44: - Minority Interest | K44: =IFERROR((C44/$C44)*100, "") -> 100 | L44: =IFERROR((D44/$C44)*100, "") -> 192.85714 | M44: =IFERROR((E44/$C44)*100, "") -> -1322.9592 | N44: =IFERROR((F44/$C44)*100, "") -> 661.05442 | O44: =IFERROR((G44/$C44)*100, "") -> 401.70068
A45: Net Income, GAAP | B45: 1713.5 | C45: 2419.6 | D45: 2230 | E45: 1729 | F45: 9257.2 | G45: 6295.9 | J45: Net Income, GAAP | K45: =IFERROR((C45/$C45)*100, "") -> 100 | L45: =IFERROR((D45/$C45)*100, "") -> 92.163994 | M45: =IFERROR((E45/$C45)*100, "") -> 71.458092 | N45: =IFERROR((F45/$C45)*100, "") -> 382.59216 | O45: =IFERROR((G45/$C45)*100, "") -> 260.20417
A46: - Preferred Dividends | B46: 0 | C46: 0 | D46: 0 | E46: 0 | F46: 0 | G46: 0 | J46: - Preferred Dividends | K46: =IFERROR((C46/$C46)*100, "") | L46: =IFERROR((D46/$C46)*100, "") | M46: =IFERROR((E46/$C46)*100, "") | N46: =IFERROR((F46/$C46)*100, "") | O46: =IFERROR((G46/$C46)*100, "")
A47: - Other Adjustments | B47: 0 | C47: 0 | D47: 0 | E47: 0 | F47: 0 | G47: 0 | J47: - Other Adjustments | K47: =IFERROR((C47/$C47)*100, "") | L47: =IFERROR((D47/$C47)*100, "") | M47: =IFERROR((E47/$C47)*100, "") | N47: =IFERROR((F47/$C47)*100, "") | O47: =IFERROR((G47/$C47)*100, "")
A48: Net Income Avail to Common, GAAP | B48: 1713.5 | C48: 2419.6 | D48: 2230 | E48: 1729 | F48: 9257.2 | G48: 6295.9 | J48: Net Income Avail to Common, GAAP | K48: =IFERROR((C48/$C48)*100, "") -> 100 | L48: =IFERROR((D48/$C48)*100, "") -> 92.163994 | M48: =IFERROR((E48/$C48)*100, "") -> 71.458092 | N48: =IFERROR((F48/$C48)*100, "") -> 382.59216 | O48: =IFERROR((G48/$C48)*100, "") -> 260.20417
K49: =IFERROR((C49/$C49)*100, "") | L49: =IFERROR((D49/$C49)*100, "") | M49: =IFERROR((E49/$C49)*100, "") | N49: =IFERROR((F49/$C49)*100, "") | O49: =IFERROR((G49/$C49)*100, "")
A50: Net Income Avail to Common, Adj | B50: 1641.82 | C50: 2283.17 | D50: 2138.93 | E50: 1655.85 | F50: 8114.37 | G50: 6544.89 | J50: Net Income Avail to Common, Adj | K50: =IFERROR((C50/$C50)*100, "") -> 100 | L50: =IFERROR((D50/$C50)*100, "") -> 93.682468 | M50: =IFERROR((E50/$C50)*100, "") -> 72.524166 | N50: =IFERROR((F50/$C50)*100, "") -> 355.39929 | O50: =IFERROR((G50/$C50)*100, "") -> 286.65802
A51: Net Abnormal Losses (Gains) | B51: -71.68 | C51: -136.43 | D51: -91.07 | E51: -73.15 | F51: 262.57 | G51: 248.99 | J51: Net Abnormal Losses (Gains) | K51: =IFERROR((C51/$C51)*100, "") -> 100 | L51: =IFERROR((D51/$C51)*100, "") -> 66.752181 | M51: =IFERROR((E51/$C51)*100, "") -> 53.61724 | N51: =IFERROR((F51/$C51)*100, "") -> -192.45767 | O51: =IFERROR((G51/$C51)*100, "") -> -182.50385
A52: Net Extraordinary Losses (Gains) | B52: 0 | C52: 0 | D52: 0 | E52: 0 | F52: -1405.4 | G52: 0 | J52: Net Extraordinary Losses (Gains) | K52: =IFERROR((C52/$C52)*100, "") | L52: =IFERROR((D52/$C52)*100, "") | M52: =IFERROR((E52/$C52)*100, "") | N52: =IFERROR((F52/$C52)*100, "") | O52: =IFERROR((G52/$C52)*100, "")
K53: =IFERROR((C53/$C53)*100, "") | L53: =IFERROR((D53/$C53)*100, "") | M53: =IFERROR((E53/$C53)*100, "") | N53: =IFERROR((F53/$C53)*100, "") | O53: =IFERROR((G53/$C53)*100, "")
A54: Basic Weighted Avg Shares | B54: 245.6955 | C54: 245.6955 | D54: 245.7 | E54: 245.6955 | F54: 245.6955 | G54: 245.6955 | J54: Basic Weighted Avg Shares | K54: =IFERROR((C54/$C54)*100, "") -> 100 | L54: =IFERROR((D54/$C54)*100, "") -> 100.00183 | M54: =IFERROR((E54/$C54)*100, "") -> 100 | N54: =IFERROR((F54/$C54)*100, "") -> 100 | O54: =IFERROR((G54/$C54)*100, "") -> 100
A55: Basic EPS, GAAP | B55: 6.97 | C55: 9.85 | D55: 9.0761 | E55: 7.04 | F55: 37.68 | G55: 25.62 | J55: Basic EPS, GAAP | K55: =IFERROR((C55/$C55)*100, "") -> 100 | L55: =IFERROR((D55/$C55)*100, "") -> 92.143147 | M55: =IFERROR((E55/$C55)*100, "") -> 71.472081 | N55: =IFERROR((F55/$C55)*100, "") -> 382.53807 | O55: =IFERROR((G55/$C55)*100, "") -> 260.10152
A56: Basic EPS from Cont Ops, GAAP | B56: 6.97 | C56: 9.85 | D56: 9.0761 | E56: 7.04 | F56: 31.96 | G56: 25.62 | J56: Basic EPS from Cont Ops, GAAP | K56: =IFERROR((C56/$C56)*100, "") -> 100 | L56: =IFERROR((D56/$C56)*100, "") -> 92.143147 | M56: =IFERROR((E56/$C56)*100, "") -> 71.472081 | N56: =IFERROR((F56/$C56)*100, "") -> 324.46701 | O56: =IFERROR((G56/$C56)*100, "") -> 260.10152
A57: Basic EPS from Cont Ops, Adjusted | B57: 6.6823 | C57: 9.2927 | D57: 8.7055 | E57: 6.7394 | F57: 33.0262 | G57: 26.6382 | J57: Basic EPS from Cont Ops, Adjusted | K57: =IFERROR((C57/$C57)*100, "") -> 100 | L57: =IFERROR((D57/$C57)*100, "") -> 93.681061 | M57: =IFERROR((E57/$C57)*100, "") -> 72.523594 | N57: =IFERROR((F57/$C57)*100, "") -> 355.3994 | O57: =IFERROR((G57/$C57)*100, "") -> 286.65727
K58: =IFERROR((C58/$C58)*100, "") | L58: =IFERROR((D58/$C58)*100, "") | M58: =IFERROR((E58/$C58)*100, "") | N58: =IFERROR((F58/$C58)*100, "") | O58: =IFERROR((G58/$C58)*100, "")
A59: Diluted Weighted Avg Shares | B59: 245.6955 | C59: 245.6955 | D59: 245.7 | E59: 245.6955 | F59: 245.6955 | G59: 245.6955 | J59: Diluted Weighted Avg Shares | K59: =IFERROR((C59/$C59)*100, "") -> 100 | L59: =IFERROR((D59/$C59)*100, "") -> 100.00183 | M59: =IFERROR((E59/$C59)*100, "") -> 100 | N59: =IFERROR((F59/$C59)*100, "") -> 100 | O59: =IFERROR((G59/$C59)*100, "") -> 100
A60: Diluted EPS, GAAP | B60: 6.97 | C60: 9.85 | D60: 9.0761 | E60: 7.04 | F60: 37.68 | G60: 25.62 | J60: Diluted EPS, GAAP | K60: =IFERROR((C60/$C60)*100, "") -> 100 | L60: =IFERROR((D60/$C60)*100, "") -> 92.143147 | M60: =IFERROR((E60/$C60)*100, "") -> 71.472081 | N60: =IFERROR((F60/$C60)*100, "") -> 382.53807 | O60: =IFERROR((G60/$C60)*100, "") -> 260.10152
A61: Diluted EPS from Cont Ops, GAAP | B61: 6.97 | C61: 9.85 | D61: 9.0761 | E61: 7.04 | F61: 31.96 | G61: 25.62 | J61: Diluted EPS from Cont Ops, GAAP | K61: =IFERROR((C61/$C61)*100, "") -> 100 | L61: =IFERROR((D61/$C61)*100, "") -> 92.143147 | M61: =IFERROR((E61/$C61)*100, "") -> 71.472081 | N61: =IFERROR((F61/$C61)*100, "") -> 324.46701 | O61: =IFERROR((G61/$C61)*100, "") -> 260.10152
A62: Diluted EPS from Cont Ops, Adjusted | B62: 6.6823 | C62: 9.2927 | D62: 8.7055 | E62: 6.7394 | F62: 33.0262 | G62: 26.6382 | J62: Diluted EPS from Cont Ops, Adjusted | K62: =IFERROR((C62/$C62)*100, "") -> 100 | L62: =IFERROR((D62/$C62)*100, "") -> 93.681061 | M62: =IFERROR((E62/$C62)*100, "") -> 72.523594 | N62: =IFERROR((F62/$C62)*100, "") -> 355.3994 | O62: =IFERROR((G62/$C62)*100, "") -> 286.65727
K63: =IFERROR((C63/$C63)*100, "") | L63: =IFERROR((D63/$C63)*100, "") | M63: =IFERROR((E63/$C63)*100, "") | N63: =IFERROR((F63/$C63)*100, "") | O63: =IFERROR((G63/$C63)*100, "")
A66: Horizontal Analysis of the Balance sheet
A68: In Millions of INR except Per Share | B68: FY 2018 | C68: FY 2019 | D68: FY 2020 | E68: FY 2021 | F68: FY 2022 | G68: FY 2023 | J68: In Millions of INR except Per Share | K68: FY 2019 | L68: FY 2020 | M68: FY 2021 | N68: FY 2022 | O68: FY 2023
A69: 12 Months Ending | B69: 03/31/2018 | C69: 03/31/2019 | D69: 03/31/2020 | E69: 03/31/2021 | F69: 03/31/2022 | G69: 03/31/2023 | J69: 12 Months Ending | K69: 03/31/2019 | L69: 03/31/2020 | M69: 03/31/2021 | N69: 03/31/2022 | O69: 03/31/2023
A70: Total Assets | J70: Total Assets
A71: + Cash, Cash Equivalents & STI | B71: 3545.7 | C71: 2651.3 | D71: 3070.3 | E71: 4123.6 | F71: 7903.1 | G71: 14794.2 | J71: + Cash, Cash Equivalents & STI | K71: =IFERROR(C71/$C71*100, "") -> 100 | L71: =IFERROR(D71/$C71*100, "") -> 115.80357 | M71: =IFERROR(E71/$C71*100, "") -> 155.53125 | N71: =IFERROR(F71/$C71*100, "") -> 298.08396 | O71: =IFERROR(G71/$C71*100, "") -> 557.99796
A72: + Cash & Cash Equivalents | B72: 2439.4 | C72: 2400.2 | D72: 2999.8 | E72: 3812.2 | F72: 6443.5 | G72: 13087.6 | J72: + Cash & Cash Equivalents | K72: =IFERROR(C72/$C72*100, "") -> 100 | L72: =IFERROR(D72/$C72*100, "") -> 124.98125 | M72: =IFERROR(E72/$C72*100, "") -> 158.82843 | N72: =IFERROR(F72/$C72*100, "") -> 268.4568 | O72: =IFERROR(G72/$C72*100, "") -> 545.27123
A73: + ST Investments | B73: 1106.3 | C73: 251.1 | D73: 70.5 | E73: 311.4 | F73: 1459.6 | G73: 1706.6 | J73: + ST Investments | K73: =IFERROR(C73/$C73*100, "") -> 100 | L73: =IFERROR(D73/$C73*100, "") -> 28.076464 | M73: =IFERROR(E73/$C73*100, "") -> 124.01434 | N73: =IFERROR(F73/$C73*100, "") -> 581.28236 | O73: =IFERROR(G73/$C73*100, "") -> 679.64954
A74: + Accounts & Notes Receiv | B74: 8386.3 | C74: 9421.5 | D74: 11500.9 | E74: 21757 | F74: 30762.5 | G74: 20380.5 | J74: + Accounts & Notes Receiv | K74: =IFERROR(C74/$C74*100, "") -> 100 | L74: =IFERROR(D74/$C74*100, "") -> 122.0708 | M74: =IFERROR(E74/$C74*100, "") -> 230.92926 | N74: =IFERROR(F74/$C74*100, "") -> 326.51382 | O74: =IFERROR(G74/$C74*100, "") -> 216.31906
A75: + Accounts Receivable, Net | B75: 8386.3 | C75: 9421.5 | D75: 11500.9 | E75: 21757 | F75: 30762.5 | G75: 20380.5 | J75: + Accounts Receivable, Net | K75: =IFERROR(C75/$C75*100, "") -> 100 | L75: =IFERROR(D75/$C75*100, "") -> 122.0708 | M75: =IFERROR(E75/$C75*100, "") -> 230.92926 | N75: =IFERROR(F75/$C75*100, "") -> 326.51382 | O75: =IFERROR(G75/$C75*100, "") -> 216.31906
A76: + Notes Receivable, Net | B76: 0 | C76: 0 | D76: 0 | E76: 0 | F76: 0 | G76: 0 | J76: + Notes Receivable, Net | K76: =IFERROR(C76/$C76*100, "") | L76: =IFERROR(D76/$C76*100, "") | M76: =IFERROR(E76/$C76*100, "") | N76: =IFERROR(F76/$C76*100, "") | O76: =IFERROR(G76/$C76*100, "")
A77: + Unbilled Revenues | B77: 0 | C77: — | D77: — | E77: 4231.1 | F77: 7093.2 | G77: 4231.8 | J77: + Unbilled Revenues | K77: =IFERROR(C77/$C77*100, "") | L77: =IFERROR(D77/$C77*100, "") | M77: =IFERROR(E77/$C77*100, "") | N77: =IFERROR(F77/$C77*100, "") | O77: =IFERROR(G77/$C77*100, "")
A78: + Inventories | B78: 95.8 | C78: 88.8 | D78: 77.6 | E78: 97.1 | F78: 57.1 | G78: 24.4 | J78: + Inventories | K78: =IFERROR(C78/$C78*100, "") -> 100 | L78: =IFERROR(D78/$C78*100, "") -> 87.387387 | M78: =IFERROR(E78/$C78*100, "") -> 109.34685 | N78: =IFERROR(F78/$C78*100, "") -> 64.301802 | O78: =IFERROR(G78/$C78*100, "") -> 27.477477
A79: + Raw Materials | B79: 0.5 | C79: 0 | D79: 0 | E79: 0 | F79: 0 | G79: 0 | J79: + Raw Materials | K79: =IFERROR(C79/$C79*100, "") | L79: =IFERROR(D79/$C79*100, "") | M79: =IFERROR(E79/$C79*100, "") | N79: =IFERROR(F79/$C79*100, "") | O79: =IFERROR(G79/$C79*100, "")
A80: + Work In Process | B80: 0 | C80: 0 | D80: 0 | E80: 0 | F80: 0 | G80: 0 | J80: + Work In Process | K80: =IFERROR(C80/$C80*100, "") | L80: =IFERROR(D80/$C80*100, "") | M80: =IFERROR(E80/$C80*100, "") | N80: =IFERROR(F80/$C80*100, "") | O80: =IFERROR(G80/$C80*100, "")
A81: + Finished Goods | B81: 0 | C81: 88.8 | D81: 77.6 | E81: 37.5 | F81: 29.2 | G81: 24.4 | J81: + Finished Goods | K81: =IFERROR(C81/$C81*100, "") -> 100 | L81: =IFERROR(D81/$C81*100, "") -> 87.387387 | M81: =IFERROR(E81/$C81*100, "") -> 42.22973 | N81: =IFERROR(F81/$C81*100, "") -> 32.882883 | O81: =IFERROR(G81/$C81*100, "") -> 27.477477
A82: + Other Inventory | B82: 95.3 | C82: 0 | D82: 0 | E82: 59.6 | F82: 27.9 | G82: 0 | J82: + Other Inventory | K82: =IFERROR(C82/$C82*100, "") | L82: =IFERROR(D82/$C82*100, "") | M82: =IFERROR(E82/$C82*100, "") | N82: =IFERROR(F82/$C82*100, "") | O82: =IFERROR(G82/$C82*100, "")
A83: + Other ST Assets | B83: 2079.7 | C83: 4567.9 | D83: 8224.5 | E83: 4946.7 | F83: 6987.1 | G83: 4944.5 | J83: + Other ST Assets | K83: =IFERROR(C83/$C83*100, "") -> 100 | L83: =IFERROR(D83/$C83*100, "") -> 180.04991 | M83: =IFERROR(E83/$C83*100, "") -> 108.29265 | N83: =IFERROR(F83/$C83*100, "") -> 152.96088 | O83: =IFERROR(G83/$C83*100, "") -> 108.24449
A84: + Prepaid Expenses | B84: 608.7 | C84: 1139.6 | D84: 998.3 | E84: 1077.4 | F84: 2464.8 | G84: 1573.2 | J84: + Prepaid Expenses | K84: =IFERROR(C84/$C84*100, "") -> 100 | L84: =IFERROR(D84/$C84*100, "") -> 87.600913 | M84: =IFERROR(E84/$C84*100, "") -> 94.541945 | N84: =IFERROR(F84/$C84*100, "") -> 216.28642 | O84: =IFERROR(G84/$C84*100, "") -> 138.04844
A85: + Derivative & Hedging Assets | B85: 0 | C85: 0 | D85: 0 | E85: 0 | F85: 0 | G85: — | J85: + Derivative & Hedging Assets | K85: =IFERROR(C85/$C85*100, "") | L85: =IFERROR(D85/$C85*100, "") | M85: =IFERROR(E85/$C85*100, "") | N85: =IFERROR(F85/$C85*100, "") | O85: =IFERROR(G85/$C85*100, "")
A86: + Assets Held-for-Sale | B86: 124.3 | C86: 137.6 | D86: 0 | E86: 1674.7 | F86: 2465 | G86: 978.8 | J86: + Assets Held-for-Sale | K86: =IFERROR(C86/$C86*100, "") -> 100 | L86: =IFERROR(D86/$C86*100, "") -> 0 | M86: =IFERROR(E86/$C86*100, "") -> 1217.0785 | N86: =IFERROR(F86/$C86*100, "") -> 1791.4244 | O86: =IFERROR(G86/$C86*100, "") -> 711.33721
A87: + Deferred Tax Assets | B87: — | C87: — | D87: — | E87: — | F87: — | G87: — | J87: + Deferred Tax Assets | K87: =IFERROR(C87/$C87*100, "") | L87: =IFERROR(D87/$C87*100, "") | M87: =IFERROR(E87/$C87*100, "") | N87: =IFERROR(F87/$C87*100, "") | O87: =IFERROR(G87/$C87*100, "")
A88: + Taxes Receivable | B88: 290.5 | C88: 120.2 | D88: 130.2 | E88: 128 | F88: 108.7 | G88: 173 | J88: + Taxes Receivable | K88: =IFERROR(C88/$C88*100, "") -> 100 | L88: =IFERROR(D88/$C88*100, "") -> 108.31947 | M88: =IFERROR(E88/$C88*100, "") -> 106.48918 | N88: =IFERROR(F88/$C88*100, "") -> 90.432612 | O88: =IFERROR(G88/$C88*100, "") -> 143.92679
A89: + Misc ST Assets | B89: 1056.2 | C89: 3170.5 | D89: 7096 | E89: 2066.6 | F89: 1948.6 | G89: 2219.5 | J89: + Misc ST Assets | K89: =IFERROR(C89/$C89*100, "") -> 100 | L89: =IFERROR(D89/$C89*100, "") -> 223.81328 | M89: =IFERROR(E89/$C89*100, "") -> 65.182148 | N89: =IFERROR(F89/$C89*100, "") -> 61.460337 | O89: =IFERROR(G89/$C89*100, "") -> 70.004731
A90: Total Current Assets | B90: 14107.5 | C90: 16729.5 | D90: 22873.3 | E90: 35155.5 | F90: 52803 | G90: 44375.4 | J90: Total Current Assets | K90: =IFERROR(C90/$C90*100, "") -> 100 | L90: =IFERROR(D90/$C90*100, "") -> 136.72435 | M90: =IFERROR(E90/$C90*100, "") -> 210.14077 | N90: =IFERROR(F90/$C90*100, "") -> 315.62808 | O90: =IFERROR(G90/$C90*100, "") -> 265.2524
A91: + Property, Plant & Equip, Net | B91: 10974.6 | C91: 13013.5 | D91: 16824.3 | E91: 20670.8 | F91: 21863.6 | G91: 8157.5 | J91: + Property, Plant & Equip, Net | K91: =IFERROR(C91/$C91*100, "") -> 100 | L91: =IFERROR(D91/$C91*100, "") -> 129.28344 | M91: =IFERROR(E91/$C91*100, "") -> 158.8412 | N91: =IFERROR(F91/$C91*100, "") -> 168.00707 | O91: =IFERROR(G91/$C91*100, "") -> 62.684904
A92: + Property, Plant & Equip | B92: 14808.8 | C92: 17871.2 | D92: 22217.4 | E92: 27489 | F92: 28882.5 | G92: 11604.7 | J92: + Property, Plant & Equip | K92: =IFERROR(C92/$C92*100, "") -> 100 | L92: =IFERROR(D92/$C92*100, "") -> 124.31958 | M92: =IFERROR(E92/$C92*100, "") -> 153.81732 | N92: =IFERROR(F92/$C92*100, "") -> 161.61478 | O92: =IFERROR(G92/$C92*100, "") -> 64.935203
A93: - Accumulated Depreciation | B93: 3834.2 | C93: 4857.7 | D93: 5393.1 | E93: 6818.2 | F93: 7018.9 | G93: 3447.2 | J93: - Accumulated Depreciation | K93: =IFERROR(C93/$C93*100, "") -> 100 | L93: =IFERROR(D93/$C93*100, "") -> 111.02168 | M93: =IFERROR(E93/$C93*100, "") -> 140.35861 | N93: =IFERROR(F93/$C93*100, "") -> 144.49019 | O93: =IFERROR(G93/$C93*100, "") -> 70.963625
A94: + LT Investments & Receivables | B94: 459.9 | C94: 450.8 | D94: 1219.5 | E94: 394.8 | F94: 533.1 | G94: 180.9 | J94: + LT Investments & Receivables | K94: =IFERROR(C94/$C94*100, "") -> 100 | L94: =IFERROR(D94/$C94*100, "") -> 270.51908 | M94: =IFERROR(E94/$C94*100, "") -> 87.57764 | N94: =IFERROR(F94/$C94*100, "") -> 118.25643 | O94: =IFERROR(G94/$C94*100, "") -> 40.12866
A95: + LT Investments | B95: 459.9 | C95: 450.8 | D95: 1219.5 | E95: 394.8 | F95: 533.1 | G95: 180.9 | J95: + LT Investments | K95: =IFERROR(C95/$C95*100, "") -> 100 | L95: =IFERROR(D95/$C95*100, "") -> 270.51908 | M95: =IFERROR(E95/$C95*100, "") -> 87.57764 | N95: =IFERROR(F95/$C95*100, "") -> 118.25643 | O95: =IFERROR(G95/$C95*100, "") -> 40.12866
A96: + LT Receivables | B96: — | C96: — | D96: 0 | E96: — | F96: — | G96: — | J96: + LT Receivables | K96: =IFERROR(C96/$C96*100, "") | L96: =IFERROR(D96/$C96*100, "") | M96: =IFERROR(E96/$C96*100, "") | N96: =IFERROR(F96/$C96*100, "") | O96: =IFERROR(G96/$C96*100, "")
A97: + Other LT Assets | B97: 8550.1 | C97: 8964.5 | D97: 12219.7 | E97: 18381 | F97: 22501.3 | G97: 20653.6 | J97: + Other LT Assets | K97: =IFERROR(C97/$C97*100, "") -> 100 | L97: =IFERROR(D97/$C97*100, "") -> 136.31212 | M97: =IFERROR(E97/$C97*100, "") -> 205.04211 | N97: =IFERROR(F97/$C97*100, "") -> 251.00452 | O97: =IFERROR(G97/$C97*100, "") -> 230.39322
A98: + Total Intangible Assets | B98: 4273.4 | C98: 4161.3 | D98: 5222.1 | E98: 11000.7 | F98: 13082.8 | G98: 13448.3 | J98: + Total Intangible Assets | K98: =IFERROR(C98/$C98*100, "") -> 100 | L98: =IFERROR(D98/$C98*100, "") -> 125.49203 | M98: =IFERROR(E98/$C98*100, "") -> 264.35729 | N98: =IFERROR(F98/$C98*100, "") -> 314.39214 | O98: =IFERROR(G98/$C98*100, "") -> 323.17545
A99: + Goodwill | B99: 2880 | C99: 2850.1 | D99: 3364.6 | E99: 5664.3 | F99: 6864.6 | G99: 7433.7 | J99: + Goodwill | K99: =IFERROR(C99/$C99*100, "") -> 100 | L99: =IFERROR(D99/$C99*100, "") -> 118.052 | M99: =IFERROR(E99/$C99*100, "") -> 198.7404 | N99: =IFERROR(F99/$C99*100, "") -> 240.85471 | O99: =IFERROR(G99/$C99*100, "") -> 260.82243
A100: + Other Intangible Assets | B100: 1393.4 | C100: 1311.2 | D100: 1857.5 | E100: 5336.4 | F100: 6218.2 | G100: 6014.6 | J100: + Other Intangible Assets | K100: =IFERROR(C100/$C100*100, "") -> 100 | L100: =IFERROR(D100/$C100*100, "") -> 141.66412 | M100: =IFERROR(E100/$C100*100, "") -> 406.98597 | N100: =IFERROR(F100/$C100*100, "") -> 474.23734 | O100: =IFERROR(G100/$C100*100, "") -> 458.70958
A101: + Prepaid Expense | B101: 2.7 | C101: 80.8 | D101: 34.6 | E101: — | F101: — | G101: — | J101: + Prepaid Expense | K101: =IFERROR(C101/$C101*100, "") -> 100 | L101: =IFERROR(D101/$C101*100, "") -> 42.821782 | M101: =IFERROR(E101/$C101*100, "") | N101: =IFERROR(F101/$C101*100, "") | O101: =IFERROR(G101/$C101*100, "")
A102: + Deferred Tax Assets | B102: 974 | C102: 1097 | D102: 1219.7 | E102: 1921.7 | F102: 1793.8 | G102: 1064.5 | J102: + Deferred Tax Assets | K102: =IFERROR(C102/$C102*100, "") -> 100 | L102: =IFERROR(D102/$C102*100, "") -> 111.18505 | M102: =IFERROR(E102/$C102*100, "") -> 175.17776 | N102: =IFERROR(F102/$C102*100, "") -> 163.51869 | O102: =IFERROR(G102/$C102*100, "") -> 97.037375
A103: + Derivative & Hedging Assets | B103: 0 | C103: 0 | D103: 0 | E103: 0 | F103: 0 | G103: 0 | J103: + Derivative & Hedging Assets | K103: =IFERROR(C103/$C103*100, "") | L103: =IFERROR(D103/$C103*100, "") | M103: =IFERROR(E103/$C103*100, "") | N103: =IFERROR(F103/$C103*100, "") | O103: =IFERROR(G103/$C103*100, "")
A104: + Investments in Affiliates | B104: 2139 | C104: 2137.1 | D104: 4133.7 | E104: 2534.4 | F104: 3673.7 | G104: 3925.5 | J104: + Investments in Affiliates | K104: =IFERROR(C104/$C104*100, "") -> 100 | L104: =IFERROR(D104/$C104*100, "") -> 193.42567 | M104: =IFERROR(E104/$C104*100, "") -> 118.59061 | N104: =IFERROR(F104/$C104*100, "") -> 171.90117 | O104: =IFERROR(G104/$C104*100, "") -> 183.6835
...

Sheet Vertical Analysis - Allcargo
A1: Vertical Analysis of the Income Statement
A3: In Millions of INR except Per Share | B3: FY 2018 | C3: FY 2019 | D3: FY 2020 | E3: FY 2021 | F3: FY 2022 | G3: FY 2023 | J3: In Millions of INR except Per Share | K3: FY 2019 | L3: FY 2020 | M3: FY 2021 | N3: FY 2022 | O3: FY 2023
A4: 12 Months Ending | B4: 03/31/2018 | C4: 03/31/2019 | D4: 03/31/2020 | E4: 03/31/2021 | F4: 03/31/2022 | G4: 03/31/2023 | J4: 12 Months Ending | K4: 03/31/2019 | L4: 03/31/2020 | M4: 03/31/2021 | N4: 03/31/2022 | O4: 03/31/2023
A5: Revenue | B5: 60335.4 | C5: 68814.1 | D5: 73387 | E5: 104884.5 | F5: 190620.7 | G5: 180507.7 | J5: Revenue | K5: =IFERROR(C5/$C$5*100,"") -> 100 | L5: =IFERROR(D5/$D$5*100,"") -> 100 | M5: =IFERROR(E5/$E$5*100,"") -> 100 | N5: =IFERROR(F5/$F$5*100,"") -> 100 | O5: =IFERROR(G5/$G$5*100,"") -> 100
A6: + Sales & Services Revenue | B6: 60335.4 | C6: 68814.1 | D6: 73387 | E6: 104884.5 | F6: 190620.7 | G6: 180507.7 | J6: + Sales & Services Revenue | K6: =IFERROR(C6/$C$5*100,"") -> 100 | L6: =IFERROR(D6/$D$5*100,"") -> 100 | M6: =IFERROR(E6/$E$5*100,"") -> 100 | N6: =IFERROR(F6/$F$5*100,"") -> 100 | O6: =IFERROR(G6/$G$5*100,"") -> 100
A7: + Other Operating Income | B7: 156.5 | C7: 134.5 | D7: 75.4 | E7: 96.5 | F7: 0 | G7: 0 | J7: + Other Operating Income | K7: =IFERROR(C7/$C$5*100,"") -> 0.19545413 | L7: =IFERROR(D7/$D$5*100,"") -> 0.10274299 | M7: =IFERROR(E7/$E$5*100,"") -> 0.092005968 | N7: =IFERROR(F7/$F$5*100,"") -> 0 | O7: =IFERROR(G7/$G$5*100,"") -> 0
A8: - Operating Expenses | B8: 58311.2 | C8: 66022.8 | D8: 70689.2 | E8: 100706.6 | F8: 179578.1 | G8: 171319.9 | J8: - Operating Expenses | K8: =IFERROR(C8/$C$5*100,"") -> 95.943709 | L8: =IFERROR(D8/$D$5*100,"") -> 96.323872 | M8: =IFERROR(E8/$E$5*100,"") -> 96.016666 | N8: =IFERROR(F8/$F$5*100,"") -> 94.20703 | O8: =IFERROR(G8/$G$5*100,"") -> 94.910023
A9: + Selling, General & Admin | B9: — | C9: — | D9: — | E9: — | F9: — | G9: — | J9: + Selling, General & Admin | K9: =IFERROR(C9/$C$5*100,"") | L9: =IFERROR(D9/$D$5*100,"") | M9: =IFERROR(E9/$E$5*100,"") | N9: =IFERROR(F9/$F$5*100,"") | O9: =IFERROR(G9/$G$5*100,"")
A10: + Selling & Marketing | B10: 282.3 | C10: 248.1 | D10: 264.4 | E10: 117.2 | F10: 0 | G10: 47.8 | J10: + Selling & Marketing | K10: =IFERROR(C10/$C$5*100,"") -> 0.36053658 | L10: =IFERROR(D10/$D$5*100,"") -> 0.36028179 | M10: =IFERROR(E10/$E$5*100,"") -> 0.11174196 | N10: =IFERROR(F10/$F$5*100,"") -> 0 | O10: =IFERROR(G10/$G$5*100,"") -> 0.026480865
A11: + Research & Development | B11: 0 | C11: 0 | D11: 0 | E11: 0 | F11: — | G11: — | J11: + Research & Development | K11: =IFERROR(C11/$C$5*100,"") -> 0 | L11: =IFERROR(D11/$D$5*100,"") -> 0 | M11: =IFERROR(E11/$E$5*100,"") -> 0 | N11: =IFERROR(F11/$F$5*100,"") | O11: =IFERROR(G11/$G$5*100,"")
A12: + Depreciation & Amortization | B12: 1590.6 | C12: 1559.3 | D12: 2316 | E12: 3060.9 | F12: 2375.7 | G12: 2780.1 | J12: + Depreciation & Amortization | K12: =IFERROR(C12/$C$5*100,"") -> 2.26596 | L12: =IFERROR(D12/$D$5*100,"") -> 3.1558723 | M12: =IFERROR(E12/$E$5*100,"") -> 2.918353 | N12: =IFERROR(F12/$F$5*100,"") -> 1.246297 | O12: =IFERROR(G12/$G$5*100,"") -> 1.5401559
A13: + Prov For Doubtful Accts | B13: 298.1 | C13: -108.8 | D13: 161.8 | E13: 318.4 | F13: — | G13: — | J13: + Prov For Doubtful Accts | K13: =IFERROR(C13/$C$5*100,"") -> -0.15810713 | L13: =IFERROR(D13/$D$5*100,"") -> 0.22047502 | M13: =IFERROR(E13/$E$5*100,"") -> 0.30357202 | N13: =IFERROR(F13/$F$5*100,"") | O13: =IFERROR(G13/$G$5*100,"")
A14: + Other Operating Expense | B14: 56140.2 | C14: 64324.2 | D14: 67947 | E14: 97210.1 | F14: 177202.4 | G14: 168492 | J14: + Other Operating Expense | K14: =IFERROR(C14/$C$5*100,"") -> 93.47532 | L14: =IFERROR(D14/$D$5*100,"") -> 92.587243 | M14: =IFERROR(E14/$E$5*100,"") -> 92.682999 | N14: =IFERROR(F14/$F$5*100,"") -> 92.960733 | O14: =IFERROR(G14/$G$5*100,"") -> 93.343386
A15: Operating Income (Loss) | B15: 2180.7 | C15: 2925.8 | D15: 2773.2 | E15: 4274.4 | F15: 11042.6 | G15: 9187.8 | J15: Operating Income (Loss) | K15: =IFERROR(C15/$C$5*100,"") -> 4.2517449 | L15: =IFERROR(D15/$D$5*100,"") -> 3.7788709 | M15: =IFERROR(E15/$E$5*100,"") -> 4.07534 | N15: =IFERROR(F15/$F$5*100,"") -> 5.79297 | O15: =IFERROR(G15/$G$5*100,"") -> 5.0899768
A16: - Non-Operating (Income) Loss | B16: 60.3 | C16: 99.9 | D16: -151.1 | E16: 2788.1 | F16: -143.2 | G16: -121.3 | J16: - Non-Operating (Income) Loss | K16: =IFERROR(C16/$C$5*100,"") -> 0.14517374 | L16: =IFERROR(D16/$D$5*100,"") -> -0.20589478 | M16: =IFERROR(E16/$E$5*100,"") -> 2.6582574 | N16: =IFERROR(F16/$F$5*100,"") -> -0.075123006 | O16: =IFERROR(G16/$G$5*100,"") -> -0.067199349
A17: + Interest Expense, Net | B17: -20.2 | C17: -41.9 | D17: 3.3 | E17: 877 | F17: 162.3 | G17: -29.2 | J17: + Interest Expense, Net | K17: =IFERROR(C17/$C$5*100,"") -> -0.060888684 | L17: =IFERROR(D17/$D$5*100,"") -> 0.0044967092 | M17: =IFERROR(E17/$E$5*100,"") -> 0.83615787 | N17: =IFERROR(F17/$F$5*100,"") -> 0.085142904 | O17: =IFERROR(G17/$G$5*100,"") -> -0.016176595
A18: + Interest Expense | B18: 6 | C18: 2.5 | D18: 3.3 | E18: 980.9 | F18: 327.8 | G18: 243.7 | J18: + Interest Expense | K18: =IFERROR(C18/$C$5*100,"") -> 0.0036329764 | L18: =IFERROR(D18/$D$5*100,"") -> 0.0044967092 | M18: =IFERROR(E18/$E$5*100,"") -> 0.93521922 | N18: =IFERROR(F18/$F$5*100,"") -> 0.17196453 | O18: =IFERROR(G18/$G$5*100,"") -> 0.13500809
A19: - Interest Income | B19: 26.2 | C19: 44.4 | D19: 0 | E19: 103.9 | F19: 165.5 | G19: 272.9 | J19: - Interest Income | K19: =IFERROR(C19/$C$5*100,"") -> 0.064521661 | L19: =IFERROR(D19/$D$5*100,"") -> 0 | M19: =IFERROR(E19/$E$5*100,"") -> 0.099061348 | N19: =IFERROR(F19/$F$5*100,"") -> 0.086821631 | O19: =IFERROR(G19/$G$5*100,"") -> 0.15118469
A20: + Other Investment (Inc) Loss | B20: — | C20: — | D20: — | E20: -8 | F20: -1.9 | G20: -16 | J20: + Other Investment (Inc) Loss | K20: =IFERROR(C20/$C$5*100,"") | L20: =IFERROR(D20/$D$5*100,"") | M20: =IFERROR(E20/$E$5*100,"") -> -0.0076274378 | N20: =IFERROR(F20/$F$5*100,"") -> -0.0009967438 | O20: =IFERROR(G20/$G$5*100,"") -> -0.0088638878
A21: + Foreign Exch (Gain) Loss | B21: -2.2 | C21: -13.7 | D21: 0 | E21: 0 | F21: 0 | G21: -47.7 | J21: + Foreign Exch (Gain) Loss | K21: =IFERROR(C21/$C$5*100,"") -> -0.019908711 | L21: =IFERROR(D21/$D$5*100,"") -> 0 | M21: =IFERROR(E21/$E$5*100,"") -> 0 | N21: =IFERROR(F21/$F$5*100,"") -> 0 | O21: =IFERROR(G21/$G$5*100,"") -> -0.026425466
A22: + (Income) Loss from Affiliates | B22: -48 | C22: -52.1 | D22: -60.7 | E22: -170 | F22: -812 | G22: -174.4 | J22: + (Income) Loss from Affiliates | K22: =IFERROR(C22/$C$5*100,"") -> -0.075711228 | L22: =IFERROR(D22/$D$5*100,"") -> -0.082712197 | M22: =IFERROR(E22/$E$5*100,"") -> -0.16208305 | N22: =IFERROR(F22/$F$5*100,"") -> -0.42597682 | O22: =IFERROR(G22/$G$5*100,"") -> -0.096616377
A23: + Other Non-Op (Income) Loss | B23: 130.7 | C23: 207.6 | D23: -93.7 | E23: 2089.1 | F23: 508.4 | G23: 146 | J23: + Other Non-Op (Income) Loss | K23: =IFERROR(C23/$C$5*100,"") -> 0.30168236 | L23: =IFERROR(D23/$D$5*100,"") -> -0.12767929 | M23: =IFERROR(E23/$E$5*100,"") -> 1.99181 | N23: =IFERROR(F23/$F$5*100,"") -> 0.26670766 | O23: =IFERROR(G23/$G$5*100,"") -> 0.080882976
A24: Pretax Income (Loss), Adjusted | B24: 2120.4 | C24: 2825.9 | D24: 2924.3 | E24: 1486.3 | F24: 11185.8 | G24: 9309.1 | J24: Pretax Income (Loss), Adjusted | K24: =IFERROR(C24/$C$5*100,"") -> 4.1065712 | L24: =IFERROR(D24/$D$5*100,"") -> 3.9847657 | M24: =IFERROR(E24/$E$5*100,"") -> 1.4170826 | N24: =IFERROR(F24/$F$5*100,"") -> 5.868093 | O24: =IFERROR(G24/$G$5*100,"") -> 5.1571761
A25: - Abnormal Losses (Gains) | B25: -131.8 | C25: -194.9 | D25: -130.1 | E25: -104.5 | F25: 375.1 | G25: 355.7 | J25: - Abnormal Losses (Gains) | K25: =IFERROR(C25/$C$5*100,"") -> -0.28322684 | L25: =IFERROR(D25/$D$5*100,"") -> -0.17727935 | M25: =IFERROR(E25/$E$5*100,"") -> -0.099633406 | N25: =IFERROR(F25/$F$5*100,"") -> 0.19677821 | O25: =IFERROR(G25/$G$5*100,"") -> 0.19705531
A26: + Disposal of Assets | B26: -149.3 | C26: -127.1 | D26: 31.6 | E26: -90.6 | F26: 14.4 | G26: 3.2 | J26: + Disposal of Assets | K26: =IFERROR(C26/$C$5*100,"") -> -0.18470052 | L26: =IFERROR(D26/$D$5*100,"") -> 0.043059397 | M26: =IFERROR(E26/$E$5*100,"") -> -0.086380733 | N26: =IFERROR(F26/$F$5*100,"") -> 0.0075542688 | O26: =IFERROR(G26/$G$5*100,"") -> 0.0017727776
A27: + Asset Write-Down | B27: — | C27: — | D27: — | E27: — | F27: 555.8 | G27: 702.8 | J27: + Asset Write-Down | K27: =IFERROR(C27/$C$5*100,"") | L27: =IFERROR(D27/$D$5*100,"") | M27: =IFERROR(E27/$E$5*100,"") | N27: =IFERROR(F27/$F$5*100,"") -> 0.29157379 | O27: =IFERROR(G27/$G$5*100,"") -> 0.38934627
A28: + Impairment of Goodwill | B28: 68.6 | C28: — | D28: — | E28: — | F28: — | G28: — | J28: + Impairment of Goodwill | K28: =IFERROR(C28/$C$5*100,"") | L28: =IFERROR(D28/$D$5*100,"") | M28: =IFERROR(E28/$E$5*100,"") | N28: =IFERROR(F28/$F$5*100,"") | O28: =IFERROR(G28/$G$5*100,"")
A29: + Gain/Loss on Sale/Acquisition of Business | B29: — | C29: — | D29: -125.8 | E29: — | F29: -185.1 | G29: -278.7 | J29: + Gain/Loss on Sale/Acquisition of Business | K29: =IFERROR(C29/$C$5*100,"") | L29: =IFERROR(D29/$D$5*100,"") -> -0.17142001 | M29: =IFERROR(E29/$E$5*100,"") | N29: =IFERROR(F29/$F$5*100,"") -> -0.09710383 | O29: =IFERROR(G29/$G$5*100,"") -> -0.15439785
A30: + Sale of Investments | B30: -51.1 | C30: -67.8 | D30: -35.9 | E30: -13.9 | F30: -6.7 | G30: -50.2 | J30: + Sale of Investments | K30: =IFERROR(C30/$C$5*100,"") -> -0.098526319 | L30: =IFERROR(D30/$D$5*100,"") -> -0.048918746 | M30: =IFERROR(E30/$E$5*100,"") -> -0.013252673 | N30: =IFERROR(F30/$F$5*100,"") -> -0.0035148334 | O30: =IFERROR(G30/$G$5*100,"") -> -0.027810448
A31: + Unrealized Investments | B31: — | C31: — | D31: — | E31: — | F31: -3.3 | G31: -21.4 | J31: + Unrealized Investments | K31: =IFERROR(C31/$C$5*100,"") | L31: =IFERROR(D31/$D$5*100,"") | M31: =IFERROR(E31/$E$5*100,"") | N31: =IFERROR(F31/$F$5*100,"") -> -0.0017311866 | O31: =IFERROR(G31/$G$5*100,"") -> -0.01185545
A32: + Other Abnormal Items | B32: — | C32: — | D32: — | E32: — | F32: — | G32: — | J32: + Other Abnormal Items | K32: =IFERROR(C32/$C$5*100,"") | L32: =IFERROR(D32/$D$5*100,"") | M32: =IFERROR(E32/$E$5*100,"") | N32: =IFERROR(F32/$F$5*100,"") | O32: =IFERROR(G32/$G$5*100,"")
A33: Pretax Income (Loss), GAAP | B33: 2252.2 | C33: 3020.8 | D33: 3054.4 | E33: 1590.8 | F33: 10810.7 | G33: 8953.4 | J33: Pretax Income (Loss), GAAP | K33: =IFERROR(C33/$C$5*100,"") -> 4.389798 | L33: =IFERROR(D33/$D$5*100,"") -> 4.162045 | M33: =IFERROR(E33/$E$5*100,"") -> 1.516716 | N33: =IFERROR(F33/$F$5*100,"") -> 5.6713148 | O33: =IFERROR(G33/$G$5*100,"") -> 4.9601208
A34: - Income Tax Expense (Benefit) | B34: 512.6 | C34: 542.4 | D34: 711 | E34: 639.7 | F34: 2570.2 | G34: 2421.3 | J34: - Income Tax Expense (Benefit) | K34: =IFERROR(C34/$C$5*100,"") -> 0.78821056 | L34: =IFERROR(D34/$D$5*100,"") -> 0.96883644 | M34: =IFERROR(E34/$E$5*100,"") -> 0.609909 | N34: =IFERROR(F34/$F$5*100,"") -> 1.3483321 | O34: =IFERROR(G34/$G$5*100,"") -> 1.3413832
A35: + Current Income Tax | B35: 602.8 | C35: 925.3 | D35: 1345 | E35: 1267.7 | F35: 2803.3 | G35: 2508.2 | J35: + Current Income Tax | K35: =IFERROR(C35/$C$5*100,"") -> 1.3446372 | L35: =IFERROR(D35/$D$5*100,"") -> 1.8327497 | M35: =IFERROR(E35/$E$5*100,"") -> 1.2086629 | N35: =IFERROR(F35/$F$5*100,"") -> 1.4706168 | O35: =IFERROR(G35/$G$5*100,"") -> 1.3895252
A36: + Deferred Income Tax | B36: -90.2 | C36: -382.9 | D36: -634 | E36: -628 | F36: -233.1 | G36: -86.9 | J36: + Deferred Income Tax | K36: =IFERROR(C36/$C$5*100,"") -> -0.55642666 | L36: =IFERROR(D36/$D$5*100,"") -> -0.86391323 | M36: =IFERROR(E36/$E$5*100,"") -> -0.59875387 | N36: =IFERROR(F36/$F$5*100,"") -> -0.12228473 | O36: =IFERROR(G36/$G$5*100,"") -> -0.048141991
A37: + Tax Allowance/Credit | B37: — | C37: — | D37: — | E37: — | F37: — | G37: — | J37: + Tax Allowance/Credit | K37: =IFERROR(C37/$C$5*100,"") | L37: =IFERROR(D37/$D$5*100,"") | M37: =IFERROR(E37/$E$5*100,"") | N37: =IFERROR(F37/$F$5*100,"") | O37: =IFERROR(G37/$G$5*100,"")
A38: - (Income) Loss from Affiliates | B38: — | C38: — | D38: — | E38: — | F38: — | G38: — | J38: - (Income) Loss from Affiliates | K38: =IFERROR(C38/$C$5*100,"") | L38: =IFERROR(D38/$D$5*100,"") | M38: =IFERROR(E38/$E$5*100,"") | N38: =IFERROR(F38/$F$5*100,"") | O38: =IFERROR(G38/$G$5*100,"")
A39: Income (Loss) from Cont Ops | B39: 1739.6 | C39: 2478.4 | D39: 2343.4 | E39: 951.1 | F39: 8240.5 | G39: 6532.1 | J39: Income (Loss) from Cont Ops | K39: =IFERROR(C39/$C$5*100,"") -> 3.6015875 | L39: =IFERROR(D39/$D$5*100,"") -> 3.1932086 | M39: =IFERROR(E39/$E$5*100,"") -> 0.90680701 | N39: =IFERROR(F39/$F$5*100,"") -> 4.3229828 | O39: =IFERROR(G39/$G$5*100,"") -> 3.6187376
A40: - Net Extraordinary Losses (Gains) | B40: 0 | C40: 0 | D40: 0 | E40: 0 | F40: -1405.4 | G40: 0 | J40: - Net Extraordinary Losses (Gains) | K40: =IFERROR(C40/$C$5*100,"") -> 0 | L40: =IFERROR(D40/$D$5*100,"") -> 0 | M40: =IFERROR(E40/$E$5*100,"") -> 0 | N40: =IFERROR(F40/$F$5*100,"") -> -0.73727565 | O40: =IFERROR(G40/$G$5*100,"") -> 0
A41: + Discontinued Operations | B41: 0 | C41: 0 | D41: 0 | E41: 0 | F41: -1405.4 | G41: 0 | J41: + Discontinued Operations | K41: =IFERROR(C41/$C$5*100,"") -> 0 | L41: =IFERROR(D41/$D$5*100,"") -> 0 | M41: =IFERROR(E41/$E$5*100,"") -> 0 | N41: =IFERROR(F41/$F$5*100,"") -> -0.73727565 | O41: =IFERROR(G41/$G$5*100,"") -> 0
A42: + XO & Accounting Changes | B42: 0 | C42: 0 | D42: 0 | E42: 0 | F42: 0 | G42: 0 | J42: + XO & Accounting Changes | K42: =IFERROR(C42/$C$5*100,"") -> 0 | L42: =IFERROR(D42/$D$5*100,"") -> 0 | M42: =IFERROR(E42/$E$5*100,"") -> 0 | N42: =IFERROR(F42/$F$5*100,"") -> 0 | O42: =IFERROR(G42/$G$5*100,"") -> 0
A43: Income (Loss) Incl. MI | B43: 1739.6 | C43: 2478.4 | D43: 2343.4 | E43: 951.1 | F43: 9645.9 | G43: 6532.1 | J43: Income (Loss) Incl. MI | K43: =IFERROR(C43/$C$5*100,"") -> 3.6015875 | L43: =IFERROR(D43/$D$5*100,"") -> 3.1932086 | M43: =IFERROR(E43/$E$5*100,"") -> 0.90680701 | N43: =IFERROR(F43/$F$5*100,"") -> 5.0602584 | O43: =IFERROR(G43/$G$5*100,"") -> 3.6187376
A44: - Minority Interest | B44: 26.1 | C44: 58.8 | D44: 113.4 | E44: -777.9 | F44: 388.7 | G44: 236.2 | J44: - Minority Interest | K44: =IFERROR(C44/$C$5*100,"") -> 0.085447604 | L44: =IFERROR(D44/$D$5*100,"") -> 0.15452328 | M44: =IFERROR(E44/$E$5*100,"") -> -0.74167298 | N44: =IFERROR(F44/$F$5*100,"") -> 0.2039128 | O44: =IFERROR(G44/$G$5*100,"") -> 0.13085314
A45: Net Income, GAAP | B45: 1713.5 | C45: 2419.6 | D45: 2230 | E45: 1729 | F45: 9257.2 | G45: 6295.9 | J45: Net Income, GAAP | K45: =IFERROR(C45/$C$5*100,"") -> 3.5161399 | L45: =IFERROR(D45/$D$5*100,"") -> 3.0386853 | M45: =IFERROR(E45/$E$5*100,"") -> 1.64848 | N45: =IFERROR(F45/$F$5*100,"") -> 4.8563456 | O45: =IFERROR(G45/$G$5*100,"") -> 3.4878845
A46: - Preferred Dividends | B46: 0 | C46: 0 | D46: 0 | E46: 0 | F46: 0 | G46: 0 | J46: - Preferred Dividends | K46: =IFERROR(C46/$C$5*100,"") -> 0 | L46: =IFERROR(D46/$D$5*100,"") -> 0 | M46: =IFERROR(E46/$E$5*100,"") -> 0 | N46: =IFERROR(F46/$F$5*100,"") -> 0 | O46: =IFERROR(G46/$G$5*100,"") -> 0
A47: - Other Adjustments | B47: 0 | C47: 0 | D47: 0 | E47: 0 | F47: 0 | G47: 0 | J47: - Other Adjustments | K47: =IFERROR(C47/$C$5*100,"") -> 0 | L47: =IFERROR(D47/$D$5*100,"") -> 0 | M47: =IFERROR(E47/$E$5*100,"") -> 0 | N47: =IFERROR(F47/$F$5*100,"") -> 0 | O47: =IFERROR(G47/$G$5*100,"") -> 0
A48: Net Income Avail to Common, GAAP | B48: 1713.5 | C48: 2419.6 | D48: 2230 | E48: 1729 | F48: 9257.2 | G48: 6295.9 | J48: Net Income Avail to Common, GAAP | K48: =IFERROR(C48/$C$5*100,"") -> 3.5161399 | L48: =IFERROR(D48/$D$5*100,"") -> 3.0386853 | M48: =IFERROR(E48/$E$5*100,"") -> 1.64848 | N48: =IFERROR(F48/$F$5*100,"") -> 4.8563456 | O48: =IFERROR(G48/$G$5*100,"") -> 3.4878845
K49: =IFERROR(C49/$C$5*100,"") -> 0 | L49: =IFERROR(D49/$D$5*100,"") -> 0 | M49: =IFERROR(E49/$E$5*100,"") -> 0 | N49: =IFERROR(F49/$F$5*100,"") -> 0 | O49: =IFERROR(G49/$G$5*100,"") -> 0
A50: Net Income Avail to Common, Adj | B50: 1641.82 | C50: 2283.17 | D50: 2138.93 | E50: 1655.85 | F50: 8114.37 | G50: 6544.89 | J50: Net Income Avail to Common, Adj | K50: =IFERROR(C50/$C$5*100,"") -> 3.3178811 | L50: =IFERROR(D50/$D$5*100,"") -> 2.9145898 | M50: =IFERROR(E50/$E$5*100,"") -> 1.5787366 | N50: =IFERROR(F50/$F$5*100,"") -> 4.2568147 | O50: =IFERROR(G50/$G$5*100,"") -> 3.6258232
A51: Net Abnormal Losses (Gains) | B51: -71.68 | C51: -136.43 | D51: -91.07 | E51: -73.15 | F51: 262.57 | G51: 248.99 | J51: Net Abnormal Losses (Gains) | K51: =IFERROR(C51/$C$5*100,"") -> -0.19825879 | L51: =IFERROR(D51/$D$5*100,"") -> -0.12409555 | M51: =IFERROR(E51/$E$5*100,"") -> -0.069743384 | N51: =IFERROR(F51/$F$5*100,"") -> 0.13774475 | O51: =IFERROR(G51/$G$5*100,"") -> 0.13793871
A52: Net Extraordinary Losses (Gains) | B52: 0 | C52: 0 | D52: 0 | E52: 0 | F52: -1405.4 | G52: 0 | J52: Net Extraordinary Losses (Gains) | K52: =IFERROR(C52/$C$5*100,"") -> 0 | L52: =IFERROR(D52/$D$5*100,"") -> 0 | M52: =IFERROR(E52/$E$5*100,"") -> 0 | N52: =IFERROR(F52/$F$5*100,"") -> -0.73727565 | O52: =IFERROR(G52/$G$5*100,"") -> 0
K53: =IFERROR(C53/$C$5*100,"") -> 0 | L53: =IFERROR(D53/$D$5*100,"") -> 0 | M53: =IFERROR(E53/$E$5*100,"") -> 0 | N53: =IFERROR(F53/$F$5*100,"") -> 0 | O53: =IFERROR(G53/$G$5*100,"") -> 0
A54: Basic Weighted Avg Shares | B54: 245.6955 | C54: 245.6955 | D54: 245.7 | E54: 245.6955 | F54: 245.6955 | G54: 245.6955 | J54: Basic Weighted Avg Shares | K54: =IFERROR(C54/$C$5*100,"") -> 0.35704238 | L54: =IFERROR(D54/$D$5*100,"") -> 0.33480044 | M54: =IFERROR(E54/$E$5*100,"") -> 0.23425339 | N54: =IFERROR(F54/$F$5*100,"") -> 0.12889235 | O54: =IFERROR(G54/$G$5*100,"") -> 0.13611358
A55: Basic EPS, GAAP | B55: 6.97 | C55: 9.85 | D55: 9.0761 | E55: 7.04 | F55: 37.68 | G55: 25.62 | J55: Basic EPS, GAAP | K55: =IFERROR(C55/$C$5*100,"") -> 0.014313927 | L55: =IFERROR(D55/$D$5*100,"") -> 0.012367449 | M55: =IFERROR(E55/$E$5*100,"") -> 0.0067121453 | N55: =IFERROR(F55/$F$5*100,"") -> 0.019767003 | O55: =IFERROR(G55/$G$5*100,"") -> 0.0141933
A56: Basic EPS from Cont Ops, GAAP | B56: 6.97 | C56: 9.85 | D56: 9.0761 | E56: 7.04 | F56: 31.96 | G56: 25.62 | J56: Basic EPS from Cont Ops, GAAP | K56: =IFERROR(C56/$C$5*100,"") -> 0.014313927 | L56: =IFERROR(D56/$D$5*100,"") -> 0.012367449 | M56: =IFERROR(E56/$E$5*100,"") -> 0.0067121453 | N56: =IFERROR(F56/$F$5*100,"") -> 0.01676628 | O56: =IFERROR(G56/$G$5*100,"") -> 0.0141933
A57: Basic EPS from Cont Ops, Adjusted | B57: 6.6823 | C57: 9.2927 | D57: 8.7055 | E57: 6.7394 | F57: 33.0262 | G57: 26.6382 | J57: Basic EPS from Cont Ops, Adjusted | K57: =IFERROR(C57/$C$5*100,"") -> 0.013504064 | L57: =IFERROR(D57/$D$5*100,"") -> 0.011862455 | M57: =IFERROR(E57/$E$5*100,"") -> 0.0064255443 | N57: =IFERROR(F57/$F$5*100,"") -> 0.01732561 | O57: =IFERROR(G57/$G$5*100,"") -> 0.014757376
K58: =IFERROR(C58/$C$5*100,"") -> 0 | L58: =IFERROR(D58/$D$5*100,"") -> 0 | M58: =IFERROR(E58/$E$5*100,"") -> 0 | N58: =IFERROR(F58/$F$5*100,"") -> 0 | O58: =IFERROR(G58/$G$5*100,"") -> 0
A59: Diluted Weighted Avg Shares | B59: 245.6955 | C59: 245.6955 | D59: 245.7 | E59: 245.6955 | F59: 245.6955 | G59: 245.6955 | J59: Diluted Weighted Avg Shares | K59: =IFERROR(C59/$C$5*100,"") -> 0.35704238 | L59: =IFERROR(D59/$D$5*100,"") -> 0.33480044 | M59: =IFERROR(E59/$E$5*100,"") -> 0.23425339 | N59: =IFERROR(F59/$F$5*100,"") -> 0.12889235 | O59: =IFERROR(G59/$G$5*100,"") -> 0.13611358
A60: Diluted EPS, GAAP | B60: 6.97 | C60: 9.85 | D60: 9.0761 | E60: 7.04 | F60: 37.68 | G60: 25.62 | J60: Diluted EPS, GAAP | K60: =IFERROR(C60/$C$5*100,"") -> 0.014313927 | L60: =IFERROR(D60/$D$5*100,"") -> 0.012367449 | M60: =IFERROR(E60/$E$5*100,"") -> 0.0067121453 | N60: =IFERROR(F60/$F$5*100,"") -> 0.019767003 | O60: =IFERROR(G60/$G$5*100,"") -> 0.0141933
A61: Diluted EPS from Cont Ops, GAAP | B61: 6.97 | C61: 9.85 | D61: 9.0761 | E61: 7.04 | F61: 31.96 | G61: 25.62 | J61: Diluted EPS from Cont Ops, GAAP | K61: =IFERROR(C61/$C$5*100,"") -> 0.014313927 | L61: =IFERROR(D61/$D$5*100,"") -> 0.012367449 | M61: =IFERROR(E61/$E$5*100,"") -> 0.0067121453 | N61: =IFERROR(F61/$F$5*100,"") -> 0.01676628 | O61: =IFERROR(G61/$G$5*100,"") -> 0.0141933
A62: Diluted EPS from Cont Ops, Adjusted | B62: 6.6823 | C62: 9.2927 | D62: 8.7055 | E62: 6.7394 | F62: 33.0262 | G62: 26.6382 | J62: Diluted EPS from Cont Ops, Adjusted | K62: =IFERROR(C62/$C$5*100,"") -> 0.013504064 | L62: =IFERROR(D62/$D$5*100,"") -> 0.011862455 | M62: =IFERROR(E62/$E$5*100,"") -> 0.0064255443 | N62: =IFERROR(F62/$F$5*100,"") -> 0.01732561 | O62: =IFERROR(G62/$G$5*100,"") -> 0.014757376
K63: =IFERROR(C63/$C$5*100,"") -> 0 | L63: =IFERROR(D63/$D$5*100,"") -> 0 | M63: =IFERROR(E63/$E$5*100,"") -> 0 | N63: =IFERROR(F63/$F$5*100,"") -> 0 | O63: =IFERROR(G63/$G$5*100,"") -> 0
A66: Vertical Analysis of the Balance sheet
A68: In Millions of INR except Per Share | B68: FY 2018 | C68: FY 2019 | D68: FY 2020 | E68: FY 2021 | F68: FY 2022 | G68: FY 2023 | J68: In Millions of INR except Per Share | K68: FY 2019 | L68: FY 2020 | M68: FY 2021 | N68: FY 2022 | O68: FY 2023
A69: 12 Months Ending | B69: 03/31/2018 | C69: 03/31/2019 | D69: 03/31/2020 | E69: 03/31/2021 | F69: 03/31/2022 | G69: 03/31/2023 | J69: 12 Months Ending | K69: 03/31/2019 | L69: 03/31/2020 | M69: 03/31/2021 | N69: 03/31/2022 | O69: 03/31/2023
A70: Total Assets | J70: Total Assets
A71: + Cash, Cash Equivalents & STI | B71: 3545.7 | C71: 2651.3 | D71: 3070.3 | E71: 4123.6 | F71: 7903.1 | G71: 14794.2 | J71: + Cash, Cash Equivalents & STI | K71: =IFERROR(C71/$C$71*100,"") -> 100 | L71: =IFERROR(D71/$D$71*100,"") -> 100 | M71: =IFERROR(E71/$E$71*100,"") -> 100 | N71: =IFERROR(F71/$F$71*100,"") -> 100 | O71: =IFERROR(G71/$G$71*100,"") -> 100
A72: + Cash & Cash Equivalents | B72: 2439.4 | C72: 2400.2 | D72: 2999.8 | E72: 3812.2 | F72: 6443.5 | G72: 13087.6 | J72: + Cash & Cash Equivalents | K72: =IFERROR(C72/$C$71*100,"") -> 90.529174 | L72: =IFERROR(D72/$D$71*100,"") -> 97.703807 | M72: =IFERROR(E72/$E$71*100,"") -> 92.448346 | N72: =IFERROR(F72/$F$71*100,"") -> 81.531298 | O72: =IFERROR(G72/$G$71*100,"") -> 88.464398
A73: + ST Investments | B73: 1106.3 | C73: 251.1 | D73: 70.5 | E73: 311.4 | F73: 1459.6 | G73: 1706.6 | J73: + ST Investments | K73: =IFERROR(C73/$C$71*100,"") -> 9.4708256 | L73: =IFERROR(D73/$D$71*100,"") -> 2.2961926 | M73: =IFERROR(E73/$E$71*100,"") -> 7.5516539 | N73: =IFERROR(F73/$F$71*100,"") -> 18.468702 | O73: =IFERROR(G73/$G$71*100,"") -> 11.535602
A74: + Accounts & Notes Receiv | B74: 8386.3 | C74: 9421.5 | D74: 11500.9 | E74: 21757 | F74: 30762.5 | G74: 20380.5 | J74: + Accounts & Notes Receiv | K74: =IFERROR(C74/$C$71*100,"") -> 355.35398 | L74: =IFERROR(D74/$D$71*100,"") -> 374.58555 | M74: =IFERROR(E74/$E$71*100,"") -> 527.6215 | N74: =IFERROR(F74/$F$71*100,"") -> 389.24599 | O74: =IFERROR(G74/$G$71*100,"") -> 137.76007
A75: + Accounts Receivable, Net | B75: 8386.3 | C75: 9421.5 | D75: 11500.9 | E75: 21757 | F75: 30762.5 | G75: 20380.5 | J75: + Accounts Receivable, Net | K75: =IFERROR(C75/$C$71*100,"") -> 355.35398 | L75: =IFERROR(D75/$D$71*100,"") -> 374.58555 | M75: =IFERROR(E75/$E$71*100,"") -> 527.6215 | N75: =IFERROR(F75/$F$71*100,"") -> 389.24599 | O75: =IFERROR(G75/$G$71*100,"") -> 137.76007
A76: + Notes Receivable, Net | B76: 0 | C76: 0 | D76: 0 | E76: 0 | F76: 0 | G76: 0 | J76: + Notes Receivable, Net | K76: =IFERROR(C76/$C$71*100,"") -> 0 | L76: =IFERROR(D76/$D$71*100,"") -> 0 | M76: =IFERROR(E76/$E$71*100,"") -> 0 | N76: =IFERROR(F76/$F$71*100,"") -> 0 | O76: =IFERROR(G76/$G$71*100,"") -> 0
A77: + Unbilled Revenues | B77: 0 | C77: — | D77: — | E77: 4231.1 | F77: 7093.2 | G77: 4231.8 | J77: + Unbilled Revenues | K77: =IFERROR(C77/$C$71*100,"") | L77: =IFERROR(D77/$D$71*100,"") | M77: =IFERROR(E77/$E$71*100,"") -> 102.60695 | N77: =IFERROR(F77/$F$71*100,"") -> 89.752123 | O77: =IFERROR(G77/$G$71*100,"") -> 28.604453
A78: + Inventories | B78: 95.8 | C78: 88.8 | D78: 77.6 | E78: 97.1 | F78: 57.1 | G78: 24.4 | J78: + Inventories | K78: =IFERROR(C78/$C$71*100,"") -> 3.3493003 | L78: =IFERROR(D78/$D$71*100,"") -> 2.5274403 | M78: =IFERROR(E78/$E$71*100,"") -> 2.3547386 | N78: =IFERROR(F78/$F$71*100,"") -> 0.7225013 | O78: =IFERROR(G78/$G$71*100,"") -> 0.1649295
A79: + Raw Materials | B79: 0.5 | C79: 0 | D79: 0 | E79: 0 | F79: 0 | G79: 0 | J79: + Raw Materials | K79: =IFERROR(C79/$C$71*100,"") -> 0 | L79: =IFERROR(D79/$D$71*100,"") -> 0 | M79: =IFERROR(E79/$E$71*100,"") -> 0 | N79: =IFERROR(F79/$F$71*100,"") -> 0 | O79: =IFERROR(G79/$G$71*100,"") -> 0
A80: + Work In Process | B80: 0 | C80: 0 | D80: 0 | E80: 0 | F80: 0 | G80: 0 | J80: + Work In Process | K80: =IFERROR(C80/$C$71*100,"") -> 0 | L80: =IFERROR(D80/$D$71*100,"") -> 0 | M80: =IFERROR(E80/$E$71*100,"") -> 0 | N80: =IFERROR(F80/$F$71*100,"") -> 0 | O80: =IFERROR(G80/$G$71*100,"") -> 0
A81: + Finished Goods | B81: 0 | C81: 88.8 | D81: 77.6 | E81: 37.5 | F81: 29.2 | G81: 24.4 | J81: + Finished Goods | K81: =IFERROR(C81/$C$71*100,"") -> 3.3493003 | L81: =IFERROR(D81/$D$71*100,"") -> 2.5274403 | M81: =IFERROR(E81/$E$71*100,"") -> 0.90939955 | N81: =IFERROR(F81/$F$71*100,"") -> 0.36947527 | O81: =IFERROR(G81/$G$71*100,"") -> 0.1649295
A82: + Other Inventory | B82: 95.3 | C82: 0 | D82: 0 | E82: 59.6 | F82: 27.9 | G82: 0 | J82: + Other Inventory | K82: =IFERROR(C82/$C$71*100,"") -> 0 | L82: =IFERROR(D82/$D$71*100,"") -> 0 | M82: =IFERROR(E82/$E$71*100,"") -> 1.445339 | N82: =IFERROR(F82/$F$71*100,"") -> 0.35302603 | O82: =IFERROR(G82/$G$71*100,"") -> 0
A83: + Other ST Assets | B83: 2079.7 | C83: 4567.9 | D83: 8224.5 | E83: 4946.7 | F83: 6987.1 | G83: 4944.5 | J83: + Other ST Assets | K83: =IFERROR(C83/$C$71*100,"") -> 172.28907 | L83: =IFERROR(D83/$D$71*100,"") -> 267.87285 | M83: =IFERROR(E83/$E$71*100,"") -> 119.96071 | N83: =IFERROR(F83/$F$71*100,"") -> 88.409611 | O83: =IFERROR(G83/$G$71*100,"") -> 33.421882
A84: + Prepaid Expenses | B84: 608.7 | C84: 1139.6 | D84: 998.3 | E84: 1077.4 | F84: 2464.8 | G84: 1573.2 | J84: + Prepaid Expenses | K84: =IFERROR(C84/$C$71*100,"") -> 42.982688 | L84: =IFERROR(D84/$D$71*100,"") -> 32.514738 | M84: =IFERROR(E84/$E$71*100,"") -> 26.127655 | N84: =IFERROR(F84/$F$71*100,"") -> 31.187762 | O84: =IFERROR(G84/$G$71*100,"") -> 10.633897
A85: + Derivative & Hedging Assets | B85: 0 | C85: 0 | D85: 0 | E85: 0 | F85: 0 | G85: — | J85: + Derivative & Hedging Assets | K85: =IFERROR(C85/$C$71*100,"") -> 0 | L85: =IFERROR(D85/$D$71*100,"") -> 0 | M85: =IFERROR(E85/$E$71*100,"") -> 0 | N85: =IFERROR(F85/$F$71*100,"") -> 0 | O85: =IFERROR(G85/$G$71*100,"")
A86: + Assets Held-for-Sale | B86: 124.3 | C86: 137.6 | D86: 0 | E86: 1674.7 | F86: 2465 | G86: 978.8 | J86: + Assets Held-for-Sale | K86: =IFERROR(C86/$C$71*100,"") -> 5.1899068 | L86: =IFERROR(D86/$D$71*100,"") -> 0 | M86: =IFERROR(E86/$E$71*100,"") -> 40.612572 | N86: =IFERROR(F86/$F$71*100,"") -> 31.190292 | O86: =IFERROR(G86/$G$71*100,"") -> 6.6161063
A87: + Deferred Tax Assets | B87: — | C87: — | D87: — | E87: — | F87: — | G87: — | J87: + Deferred Tax Assets | K87: =IFERROR(C87/$C$71*100,"") | L87: =IFERROR(D87/$D$71*100,"") | M87: =IFERROR(E87/$E$71*100,"") | N87: =IFERROR(F87/$F$71*100,"") | O87: =IFERROR(G87/$G$71*100,"")
A88: + Taxes Receivable | B88: 290.5 | C88: 120.2 | D88: 130.2 | E88: 128 | F88: 108.7 | G88: 173 | J88: + Taxes Receivable | K88: =IFERROR(C88/$C$71*100,"") -> 4.533625 | L88: =IFERROR(D88/$D$71*100,"") -> 4.240628 | M88: =IFERROR(E88/$E$71*100,"") -> 3.1040838 | N88: =IFERROR(F88/$F$71*100,"") -> 1.3754096 | O88: =IFERROR(G88/$G$71*100,"") -> 1.1693772
A89: + Misc ST Assets | B89: 1056.2 | C89: 3170.5 | D89: 7096 | E89: 2066.6 | F89: 1948.6 | G89: 2219.5 | J89: + Misc ST Assets | K89: =IFERROR(C89/$C$71*100,"") -> 119.58285 | L89: =IFERROR(D89/$D$71*100,"") -> 231.11748 | M89: =IFERROR(E89/$E$71*100,"") -> 50.116403 | N89: =IFERROR(F89/$F$71*100,"") -> 24.656148 | O89: =IFERROR(G89/$G$71*100,"") -> 15.002501
A90: Total Current Assets | B90: 14107.5 | C90: 16729.5 | D90: 22873.3 | E90: 35155.5 | F90: 52803 | G90: 44375.4 | J90: Total Current Assets | K90: =IFERROR(C90/$C$71*100,"") -> 630.99234 | L90: =IFERROR(D90/$D$71*100,"") -> 744.98583 | M90: =IFERROR(E90/$E$71*100,"") -> 852.54389 | N90: =IFERROR(F90/$F$71*100,"") -> 668.13023 | O90: =IFERROR(G90/$G$71*100,"") -> 299.95133
A91: + Property, Plant & Equip, Net | B91: 10974.6 | C91: 13013.5 | D91: 16824.3 | E91: 20670.8 | F91: 21863.6 | G91: 8157.5 | J91: + Property, Plant & Equip, Net | K91: =IFERROR(C91/$C$71*100,"") -> 490.83468 | L91: =IFERROR(D91/$D$71*100,"") -> 547.96925 | M91: =IFERROR(E91/$E$71*100,"") -> 501.28043 | N91: =IFERROR(F91/$F$71*100,"") -> 276.64587 | O91: =IFERROR(G91/$G$71*100,"") -> 55.139852
A92: + Property, Plant & Equip | B92: 14808.8 | C92: 17871.2 | D92: 22217.4 | E92: 27489 | F92: 28882.5 | G92: 11604.7 | J92: + Property, Plant & Equip | K92: =IFERROR(C92/$C$71*100,"") -> 674.05424 | L92: =IFERROR(D92/$D$71*100,"") -> 723.6231 | M92: =IFERROR(E92/$E$71*100,"") -> 666.62625 | N92: =IFERROR(F92/$F$71*100,"") -> 365.45786 | O92: =IFERROR(G92/$G$71*100,"") -> 78.440875
A93: - Accumulated Depreciation | B93: 3834.2 | C93: 4857.7 | D93: 5393.1 | E93: 6818.2 | F93: 7018.9 | G93: 3447.2 | J93: - Accumulated Depreciation | K93: =IFERROR(C93/$C$71*100,"") -> 183.21955 | L93: =IFERROR(D93/$D$71*100,"") -> 175.65384 | M93: =IFERROR(E93/$E$71*100,"") -> 165.34581 | N93: =IFERROR(F93/$F$71*100,"") -> 88.811985 | O93: =IFERROR(G93/$G$71*100,"") -> 23.301023
A94: + LT Investments & Receivables | B94: 459.9 | C94: 450.8 | D94: 1219.5 | E94: 394.8 | F94: 533.1 | G94: 180.9 | J94: + LT Investments & Receivables | K94: =IFERROR(C94/$C$71*100,"") -> 17.00298 | L94: =IFERROR(D94/$D$71*100,"") -> 39.719246 | M94: =IFERROR(E94/$E$71*100,"") -> 9.5741585 | N94: =IFERROR(F94/$F$71*100,"") -> 6.7454543 | O94: =IFERROR(G94/$G$71*100,"") -> 1.2227765
A95: + LT Investments | B95: 459.9 | C95: 450.8 | D95: 1219.5 | E95: 394.8 | F95: 533.1 | G95: 180.9 | J95: + LT Investments | K95: =IFERROR(C95/$C$71*100,"") -> 17.00298 | L95: =IFERROR(D95/$D$71*100,"") -> 39.719246 | M95: =IFERROR(E95/$E$71*100,"") -> 9.5741585 | N95: =IFERROR(F95/$F$71*100,"") -> 6.7454543 | O95: =IFERROR(G95/$G$71*100,"") -> 1.2227765
A96: + LT Receivables | B96: — | C96: — | D96: 0 | E96: — | F96: — | G96: — | J96: + LT Receivables | K96: =IFERROR(C96/$C$71*100,"") | L96: =IFERROR(D96/$D$71*100,"") -> 0 | M96: =IFERROR(E96/$E$71*100,"") | N96: =IFERROR(F96/$F$71*100,"") | O96: =IFERROR(G96/$G$71*100,"")
A97: + Other LT Assets | B97: 8550.1 | C97: 8964.5 | D97: 12219.7 | E97: 18381 | F97: 22501.3 | G97: 20653.6 | J97: + Other LT Assets | K97: =IFERROR(C97/$C$71*100,"") -> 338.11715 | L97: =IFERROR(D97/$D$71*100,"") -> 397.99694 | M97: =IFERROR(E97/$E$71*100,"") -> 445.75129 | N97: =IFERROR(F97/$F$71*100,"") -> 284.71486 | O97: =IFERROR(G97/$G$71*100,"") -> 139.60606
A98: + Total Intangible Assets | B98: 4273.4 | C98: 4161.3 | D98: 5222.1 | E98: 11000.7 | F98: 13082.8 | G98: 13448.3 | J98: + Total Intangible Assets | K98: =IFERROR(C98/$C$71*100,"") -> 156.95319 | L98: =IFERROR(D98/$D$71*100,"") -> 170.08436 | M98: =IFERROR(E98/$E$71*100,"") -> 266.77418 | N98: =IFERROR(F98/$F$71*100,"") -> 165.5401 | O98: =IFERROR(G98/$G$71*100,"") -> 90.902516
A99: + Goodwill | B99: 2880 | C99: 2850.1 | D99: 3364.6 | E99: 5664.3 | F99: 6864.6 | G99: 7433.7 | J99: + Goodwill | K99: =IFERROR(C99/$C$71*100,"") -> 107.49821 | L99: =IFERROR(D99/$D$71*100,"") -> 109.58538 | M99: =IFERROR(E99/$E$71*100,"") -> 137.36298 | N99: =IFERROR(F99/$F$71*100,"") -> 86.859587 | O99: =IFERROR(G99/$G$71*100,"") -> 50.247394
A100: + Other Intangible Assets | B100: 1393.4 | C100: 1311.2 | D100: 1857.5 | E100: 5336.4 | F100: 6218.2 | G100: 6014.6 | J100: + Other Intangible Assets | K100: =IFERROR(C100/$C$71*100,"") -> 49.454984 | L100: =IFERROR(D100/$D$71*100,"") -> 60.498974 | M100: =IFERROR(E100/$E$71*100,"") -> 129.41119 | N100: =IFERROR(F100/$F$71*100,"") -> 78.680518 | O100: =IFERROR(G100/$G$71*100,"") -> 40.655122
A101: + Prepaid Expense | B101: 2.7 | C101: 80.8 | D101: 34.6 | E101: — | F101: — | G101: — | J101: + Prepaid Expense | K101: =IFERROR(C101/$C$71*100,"") -> 3.0475616 | L101: =IFERROR(D101/$D$71*100,"") -> 1.1269257 | M101: =IFERROR(E101/$E$71*100,"") | N101: =IFERROR(F101/$F$71*100,"") | O101: =IFERROR(G101/$G$71*100,"")
A102: + Deferred Tax Assets | B102: 974 | C102: 1097 | D102: 1219.7 | E102: 1921.7 | F102: 1793.8 | G102: 1064.5 | J102: + Deferred Tax Assets | K102: =IFERROR(C102/$C$71*100,"") -> 41.375929 | L102: =IFERROR(D102/$D$71*100,"") -> 39.72576 | M102: =IFERROR(E102/$E$71*100,"") -> 46.602483 | N102: =IFERROR(F102/$F$71*100,"") -> 22.697423 | O102: =IFERROR(G102/$G$71*100,"") -> 7.1953874
A103: + Derivative & Hedging Assets | B103: 0 | C103: 0 | D103: 0 | E103: 0 | F103: 0 | G103: 0 | J103: + Derivative & Hedging Assets | K103: =IFERROR(C103/$C$71*100,"") -> 0 | L103: =IFERROR(D103/$D$71*100,"") -> 0 | M103: =IFERROR(E103/$E$71*100,"") -> 0 | N103: =IFERROR(F103/$F$71*100,"") -> 0 | O103: =IFERROR(G103/$G$71*100,"") -> 0
A104: + Investments in Affiliates | B104: 2139 | C104: 2137.1 | D104: 4133.7 | E104: 2534.4 | F104: 3673.7 | G104: 3925.5 | J104: + Investments in Affiliates | K104: =IFERROR(C104/$C$71*100,"") -> 80.605741 | L104: =IFERROR(D104/$D$71*100,"") -> 134.63505 | M104: =IFERROR(E104/$E$71*100,"") -> 61.460859 | N104: =IFERROR(F104/$F$71*100,"") -> 46.484291 | O104: =IFERROR(G104/$G$71*100,"") -> 26.534047
...

Sheet Ratio Analysis 
A1: Liquidity Ratios
C2: FY 2019 | D2: FY 2020 | E2: FY 2021 | F2: FY 2022 | G2: FY 2023
A3: Current ratio | B3: Allcargo | C3: =roundup('Horizontal Analysis - Allcargo'!C90/'Horizontal Analysis - Allcargo'!C124,3) -> 1.13 | D3: =roundup('Horizontal Analysis - Allcargo'!D90/'Horizontal Analysis - Allcargo'!D124,3) -> 1.063 | E3: =roundup('Horizontal Analysis - Allcargo'!E90/'Horizontal Analysis - Allcargo'!E124,3) -> 0.957 | F3: =roundup('Horizontal Analysis - Allcargo'!F90/'Horizontal Analysis - Allcargo'!F124,3) -> 1.137 | G3: =roundup('Horizontal Analysis - Allcargo'!G90/'Horizontal Analysis - Allcargo'!G124,3) -> 1.328
B4: BlueDart | C4: =ROUNDUP(('BS - BlueDart'!C37/'BS - BlueDart'!C70),3) -> 2.122 | D4: =ROUNDUP(('BS - BlueDart'!D37/'BS - BlueDart'!D70),3) -> 1.592 | E4: =ROUNDUP(('BS - BlueDart'!E37/'BS - BlueDart'!E70),3) -> 1.791 | F4: =ROUNDUP(('BS - BlueDart'!F37/'BS - BlueDart'!F70),3) -> 2.563 | G4: =ROUNDUP(('BS - BlueDart'!G37/'BS - BlueDart'!G70),3) -> 2.332
B5: Delhivery | C5: =ROUNDUP(('BS - Delhivery'!B17/'BS - Delhivery'!B43),3) -> 8.543 | D5: =ROUNDUP(('BS - Delhivery'!C17/'BS - Delhivery'!C43),3) -> 3.766 | E5: =ROUNDUP(('BS - Delhivery'!D17/'BS - Delhivery'!D43),3) -> 2.969 | F5: =ROUNDUP(('BS - Delhivery'!E17/'BS - Delhivery'!E43),3) -> 2.637 | G5: =ROUNDUP(('BS - Delhivery'!F17/'BS - Delhivery'!F43),3) -> 5.417
A6: Inferences: | B6: 1. The increase in current ratio from 2020 to 2023 for Allcargo logistics suggests an improvement in a company's short-term liquidity and financial health.
B7: 2. After Benchmarking with copmpetitors, the company isnt doing as well as Delhivery or BlueDart
B8: 3. A dip in the ratio from 2019 to 2020 could have been caused by COVID 19
C9: FY 2019 | D9: FY 2020 | E9: FY 2021 | F9: FY 2022 | G9: FY 2023
A10: Cash ratio | B10: Allcargo | C10: =roundup(('Horizontal Analysis - Allcargo'!C90-'Horizontal Analysis - Allcargo'!C78)/'Horizontal Analysis - Allcargo'!C124, 3) -> 1.124 | D10: =roundup(('Horizontal Analysis - Allcargo'!D90-'Horizontal Analysis - Allcargo'!D78)/'Horizontal Analysis - Allcargo'!D124, 3) -> 1.059 | E10: =roundup(('Horizontal Analysis - Allcargo'!E90-'Horizontal Analysis - Allcargo'!E78)/'Horizontal Analysis - Allcargo'!E124, 3) -> 0.955 | F10: =roundup(('Horizontal Analysis - Allcargo'!F90-'Horizontal Analysis - Allcargo'!F78)/'Horizontal Analysis - Allcargo'!F124, 3) -> 1.135 | G10: =roundup(('Horizontal Analysis - Allcargo'!G90-'Horizontal Analysis - Allcargo'!G78)/'Horizontal Analysis - Allcargo'!G124, 3) -> 1.327
B11: BlueDart | C11: =ROUNDUP(('BS - BlueDart'!C20-'BS - BlueDart'!C10)/'BS - BlueDart'!C55, 3) -> 1.065 | D11: =ROUNDUP(('BS - BlueDart'!D20-'BS - BlueDart'!D10)/'BS - BlueDart'!D55, 3) -> 0.736 | E11: =ROUNDUP(('BS - BlueDart'!E20-'BS - BlueDart'!E10)/'BS - BlueDart'!E55, 3) -> 0.813 | F11: =ROUNDUP(('BS - BlueDart'!F20-'BS - BlueDart'!F10)/'BS - BlueDart'!F55, 3) -> 0.819 | G11: =ROUNDUP(('BS - BlueDart'!G20-'BS - BlueDart'!G10)/'BS - BlueDart'!G55, 3) -> 0.915
B12: Delhivery | C12: =ROUNDUP(('BS - Delhivery'!B17-'BS - Delhivery'!B10)/'BS - Delhivery'!B43, 3) -> 8.484 | D12: =ROUNDUP(('BS - Delhivery'!C17-'BS - Delhivery'!C10)/'BS - Delhivery'!C43, 3) -> 3.74 | E12: =ROUNDUP(('BS - Delhivery'!D17-'BS - Delhivery'!D10)/'BS - Delhivery'!D43, 3) -> 2.941 | F12: =ROUNDUP(('BS - Delhivery'!E17-'BS - Delhivery'!E10)/'BS - Delhivery'!E43, 3) -> 2.62 | G12: =ROUNDUP(('BS - Delhivery'!F17-'BS - Delhivery'!F10)/'BS - Delhivery'!F43, 3) -> 5.402
A13: Inferences: | B13: 1. The dip in the ratio for Allcargo logistic scould have been caused by COVID 19 pandemic
B14: 2. The increase from 2020 to 2023 suggests an improvement in a company's liquidity, specifically in terms of its ability to cover short-term liabilities with cash and cash equivalents
B15: 3. The order of liquidity can be Delhivery>Allcargo>BlueDart
A16: Leverage Financial Ratios
C17: FY 2019 | D17: FY 2020 | E17: FY 2021 | F17: FY 2022 | G17: FY 2023
A18: Debt to assets ratio | B18: Allcargo | C18: =roundup(('Horizontal Analysis - Allcargo'!C115+'Horizontal Analysis - Allcargo'!C125)/'Horizontal Analysis - Allcargo'!C107,3) -> 0.127 | D18: =roundup(('Horizontal Analysis - Allcargo'!D115+'Horizontal Analysis - Allcargo'!D125)/'Horizontal Analysis - Allcargo'!D107,3) -> 0.272 | E18: =roundup(('Horizontal Analysis - Allcargo'!E115+'Horizontal Analysis - Allcargo'!E125)/'Horizontal Analysis - Allcargo'!E107,3) -> 0.239 | F18: =roundup(('Horizontal Analysis - Allcargo'!F115+'Horizontal Analysis - Allcargo'!F125)/'Horizontal Analysis - Allcargo'!F107,3) -> 0.213 | G18: =roundup(('Horizontal Analysis - Allcargo'!G115+'Horizontal Analysis - Allcargo'!G125)/'Horizontal Analysis - Allcargo'!G107,3) -> 0.161
B19: BlueDart | C19: =ROUNDUP(('BS - BlueDart'!C46+'BS - BlueDart'!C56)/'BS - BlueDart'!C38,3) -> 0.274 | D19: =ROUNDUP(('BS - BlueDart'!D46+'BS - BlueDart'!D56)/'BS - BlueDart'!D38,3) -> 0.508 | E19: =ROUNDUP(('BS - BlueDart'!E46+'BS - BlueDart'!E56)/'BS - BlueDart'!E38,3) -> 0.405 | F19: =ROUNDUP(('BS - BlueDart'!F46+'BS - BlueDart'!F56)/'BS - BlueDart'!F38,3) -> 0.377 | G19: =ROUNDUP(('BS - BlueDart'!G46+'BS - BlueDart'!G56)/'BS - BlueDart'!G38,3) -> 0.348
B20: Delhivery | C20: =ROUNDUP(('BS - Delhivery'!B37+'BS - Delhivery'!B44)/'BS - Delhivery'!B31,3) -> 0.102 | D20: =ROUNDUP(('BS - Delhivery'!C37+'BS - Delhivery'!C44)/'BS - Delhivery'!C31,3) -> 0.174 | E20: =ROUNDUP(('BS - Delhivery'!D37+'BS - Delhivery'!D44)/'BS - Delhivery'!D31,3) -> 0.243 | F20: =ROUNDUP(('BS - Delhivery'!E37+'BS - Delhivery'!E44)/'BS - Delhivery'!E31,3) -> 0.134 | G20: =ROUNDUP(('BS - Delhivery'!F37+'BS - Delhivery'!F44)/'BS - Delhivery'!F31,3) -> 0.083
A21: Inferences: | B21: 1. A decrease in the debt-to-assets ratio for Allcargo Logistics typically indicates a positive financial development for a company
B22: 2. Delhivery seems to outperform Allcargo and BlueDart having the least of Debt to asset ratio across last 5 years
C23: FY 2019 | D23: FY 2020 | E23: FY 2021 | F23: FY 2022 | G23: FY 2023
A24: Debt to equity ratio | B24: Allcargo | C24: =roundup(('Horizontal Analysis - Allcargo'!C115+'Horizontal Analysis - Allcargo'!C125)/'Horizontal Analysis - Allcargo'!C148,3) -> 0.247 | D24: =roundup(('Horizontal Analysis - Allcargo'!D115+'Horizontal Analysis - Allcargo'!D125)/'Horizontal Analysis - Allcargo'!D148,3) -> 0.664 | E24: =roundup(('Horizontal Analysis - Allcargo'!E115+'Horizontal Analysis - Allcargo'!E125)/'Horizontal Analysis - Allcargo'!E148,3) -> 0.68 | F24: =roundup(('Horizontal Analysis - Allcargo'!F115+'Horizontal Analysis - Allcargo'!F125)/'Horizontal Analysis - Allcargo'!F148,3) -> 0.585 | G24: =roundup(('Horizontal Analysis - Allcargo'!G115+'Horizontal Analysis - Allcargo'!G125)/'Horizontal Analysis - Allcargo'!G148,3) -> 0.379
B25: BlueDart | C25: =ROUNDUP(('BS - BlueDart'!C46+'BS - BlueDart'!C56)/'BS - BlueDart'!C81,3) -> 0.859 | D25: =ROUNDUP(('BS - BlueDart'!D46+'BS - BlueDart'!D56)/'BS - BlueDart'!D81,3) -> 2.732 | E25: =ROUNDUP(('BS - BlueDart'!E46+'BS - BlueDart'!E56)/'BS - BlueDart'!E81,3) -> 1.981 | F25: =ROUNDUP(('BS - BlueDart'!F46+'BS - BlueDart'!F56)/'BS - BlueDart'!F81,3) -> 1.223 | G25: =ROUNDUP(('BS - BlueDart'!G46+'BS - BlueDart'!G56)/'BS - BlueDart'!G81,3) -> 0.95
B26: Delhivery | C26: =ROUNDUP(('BS - Delhivery'!B37+'BS - Delhivery'!B44)/'BS - Delhivery'!B61,3) -> 0.122 | D26: =ROUNDUP(('BS - Delhivery'!C37+'BS - Delhivery'!C44)/'BS - Delhivery'!C61,3) -> 0.239 | E26: =ROUNDUP(('BS - Delhivery'!D37+'BS - Delhivery'!D44)/'BS - Delhivery'!D61,3) -> 0.394 | F26: =ROUNDUP(('BS - Delhivery'!E37+'BS - Delhivery'!E44)/'BS - Delhivery'!E61,3) -> 0.185 | G26: =ROUNDUP(('BS - Delhivery'!F37+'BS - Delhivery'!F44)/'BS - Delhivery'!F61,3) -> 0.101
A27: Inferences: | B27: 1 An almost stable debt to equity ratio suggests that Allcargo has had a stable in the journey past 5 years
B28: 2. A suddent increase in the debt to equity ratio during the FY 2020 could be caused by the heavy debt intake during the COVID19 pandemic due to shutting down of logistics business in some regions
A29: Efficiency Ratios
C30: FY 2019 | D30: FY 2020 | E30: FY 2021 | F30: FY 2022 | G30: FY 2023
A31: Asset turnover ratio | B31: Allcargo | C31: =roundup('Horizontal Analysis - Allcargo'!C6*2/('Horizontal Analysis - Allcargo'!B90+'Horizontal Analysis - Allcargo'!C90), 3) -> 4.464 | D31: =roundup('Horizontal Analysis - Allcargo'!D6*2/('Horizontal Analysis - Allcargo'!C90+'Horizontal Analysis - Allcargo'!D90), 3) -> 3.707 | E31: =roundup('Horizontal Analysis - Allcargo'!E6*2/('Horizontal Analysis - Allcargo'!D90+'Horizontal Analysis - Allcargo'!E90), 3) -> 3.615 | F31: =roundup('Horizontal Analysis - Allcargo'!F6*2/('Horizontal Analysis - Allcargo'!E90+'Horizontal Analysis - Allcargo'!F90), 3) -> 4.335 | G31: =roundup('Horizontal Analysis - Allcargo'!G6*2/('Horizontal Analysis - Allcargo'!F90+'Horizontal Analysis - Allcargo'!G90), 3) -> 3.715
B32: BlueDart | C32: =roundup(('IS - BlueDart'!C4*2/('BS - BlueDart'!B38 +'BS - BlueDart'!C38)),3) -> 1.916 | D32: =roundup(('IS - BlueDart'!D4*2/('BS - BlueDart'!C38 +'BS - BlueDart'!D38)),3) -> 1.427 | E32: =roundup(('IS - BlueDart'!E4*2/('BS - BlueDart'!D38 +'BS - BlueDart'!E38)),3) -> 1.188 | F32: =roundup(('IS - BlueDart'!F4*2/('BS - BlueDart'!E38 +'BS - BlueDart'!F38)),3) -> 1.541 | G32: =roundup(('IS - BlueDart'!G4*2/('BS - BlueDart'!F38 +'BS - BlueDart'!G38)),3) -> 1.71
B33: Delhivery | D33: =roundup(('IS - Delhivery'!C4*2/('BS - Delhivery'!B31+'BS - Delhivery'!C31)),3) -> 0.661 | E33: =roundup(('IS - Delhivery'!D4*2/('BS - Delhivery'!C31+'BS - Delhivery'!D31)),3) -> 0.815 | F33: =roundup(('IS - Delhivery'!E4*2/('BS - Delhivery'!D31+'BS - Delhivery'!E31)),3) -> 1.072 | G33: =roundup(('IS - Delhivery'!F4*2/('BS - Delhivery'!E31+'BS - Delhivery'!F31)),3) -> 0.744
A34: Inferences: | B34: 1. A slight drop in the asset turnover ratio for Allcargo Logistics across past 5 years suggests a decline in a company's efficiency in generating sales from its assets. It may indicate that the company is not effectively utilizing its assets to generate revenue, which can be a concern for operational efficiency and profitability.
C35: FY 2019 | D35: FY 2020 | E35: FY 2021 | F35: FY 2022 | G35: FY 2023
A36: Inventory turnover ratio | B36: Allcargo | C36: ='Horizontal Analysis - Allcargo'!C6*2/('Horizontal Analysis - Allcargo'!B78+'Horizontal Analysis - Allcargo'!C78) -> 745.54821 | D36: ='Horizontal Analysis - Allcargo'!D6*2/('Horizontal Analysis - Allcargo'!C78+'Horizontal Analysis - Allcargo'!D78) -> 882.05529 | E36: ='Horizontal Analysis - Allcargo'!E6*2/('Horizontal Analysis - Allcargo'!D78+'Horizontal Analysis - Allcargo'!E78) -> 1200.7384 | F36: ='Horizontal Analysis - Allcargo'!F6*2/('Horizontal Analysis - Allcargo'!E78+'Horizontal Analysis - Allcargo'!F78) -> 2472.3826 | G36: ='Horizontal Analysis - Allcargo'!G6*2/('Horizontal Analysis - Allcargo'!F78+'Horizontal Analysis - Allcargo'!G78) -> 4429.6368
B37: BlueDart | C37: =ROUNDUP('IS - BlueDart'!C4*2/('BS - BlueDart'!B10+'BS - BlueDart'!C10), 3) -> 134.111 | D37: =ROUNDUP('IS - BlueDart'!D4*2/('BS - BlueDart'!C10+'BS - BlueDart'!D10), 3) -> 119.817 | E37: =ROUNDUP('IS - BlueDart'!E4*2/('BS - BlueDart'!D10+'BS - BlueDart'!E10), 3) -> 111.899 | F37: =ROUNDUP('IS - BlueDart'!F4*2/('BS - BlueDart'!E10+'BS - BlueDart'!F10), 3) -> 132.11 | G37: =ROUNDUP('IS - BlueDart'!G4*2/('BS - BlueDart'!F10+'BS - BlueDart'!G10), 3) -> 139.151
B38: Delhivery | C38: - | D38: =ROUNDUP('IS - Delhivery'!C4/('BS - Delhivery'!B10+'BS - Delhivery'!C10), 3) -> 68.716 | E38: =ROUNDUP('IS - Delhivery'!D4/('BS - Delhivery'!C10+'BS - Delhivery'!D10), 3) -> 83.293 | F38: =ROUNDUP('IS - Delhivery'!E4/('BS - Delhivery'!D10+'BS - Delhivery'!E10), 3) -> 134.279 | G38: =ROUNDUP('IS - Delhivery'!F4/('BS - Delhivery'!E10+'BS - Delhivery'!F10), 3) -> 161.778
A39: Inferences: | B39: 1. A high inventory turnove ratio for Allcargo logistics suggests that products are selling in a timely manner, and that sales are good in a given period. However, an inventory ratio that is too high could mean that it need to replenish inventory constantly, which could lead to stockouts.
C40: FY 2019 | D40: FY 2020 | E40: FY 2021 | F40: FY 2022 | G40: FY 2023
A41: Receivables turnover ratio | B41: Allcargo | C41: ='Horizontal Analysis - Allcargo'!C6/('Horizontal Analysis - Allcargo'!B75+'Horizontal Analysis - Allcargo'!C75) -> 3.8642673 | D41: ='Horizontal Analysis - Allcargo'!D6/('Horizontal Analysis - Allcargo'!C75+'Horizontal Analysis - Allcargo'!D75) -> 3.5075804 | E41: ='Horizontal Analysis - Allcargo'!E6/('Horizontal Analysis - Allcargo'!D75+'Horizontal Analysis - Allcargo'!E75) -> 3.1536718 | F41: ='Horizontal Analysis - Allcargo'!F6/('Horizontal Analysis - Allcargo'!E75+'Horizontal Analysis - Allcargo'!F75) -> 3.6295224 | G41: ='Horizontal Analysis - Allcargo'!G6/('Horizontal Analysis - Allcargo'!F75+'Horizontal Analysis - Allcargo'!G75) -> 3.5294703
B42: BlueDart | C42: =ROUNDUP('IS - BlueDart'!C4/('BS - BlueDart'!B8+'BS - BlueDart'!C8), 3) -> 3.476 | D42: =ROUNDUP('IS - BlueDart'!D4/('BS - BlueDart'!C8+'BS - BlueDart'!D8), 3) -> 3.116 | E42: =ROUNDUP('IS - BlueDart'!E4/('BS - BlueDart'!D8+'BS - BlueDart'!E8), 3) -> 3.144 | F42: =ROUNDUP('IS - BlueDart'!F4/('BS - BlueDart'!E8+'BS - BlueDart'!F8), 3) -> 4.018 | G42: =ROUNDUP('IS - BlueDart'!G4/('BS - BlueDart'!F8+'BS - BlueDart'!G8), 3) -> 4.252
B43: Delhivery | C43: - | D43: - | E43: - | F43: - | G43: =ROUNDUP('IS - Delhivery'!F4/('BS - Delhivery'!E8+'BS - Delhivery'!F8), 3) -> 3.737
A44: Inferences: | B44: 1. Since the ratio has been almost stagnant for all three companies it seems as if they are performing similarily across this area of evaluation
A45: Profitability Ratios
C46: FY 2019 | D46: FY 2020 | E46: FY 2021 | F46: FY 2022 | G46: FY 2023
A47: Operating margin ratio | B47: Allcargo | C47: 4.2517 | D47: 3.7789 | E47: 4.0753 | F47: 5.793 | G47: 5.09
B48: BlueDart | C48: 5.2193 | D48: 4.1828 | E48: 8.1815 | F48: 14.434 | G48: 10.5009
B49: Delhivery | C49: -108.1366 | D49: -15.3795 | E49: -13.096 | F49: -16.0184 | G49: -17.9471
A50: Inferences: | B50: 1. An increasing operating margin for Allcargo Logistics indicates that it is becoming more efficient in managing its operating expenses and generating more profit from each dollar of revenue.
B51: 2. A negetive operating margin for Delhivery indicates that a company is experiencing operating losses, indicating that its operating expenses exceed its gross profit. This is a sign of financial distress and inefficiency in managing costs.
C52: FY 2019 | D52: FY 2020 | E52: FY 2021 | F52: FY 2022 | G52: FY 2023
A53: Net profit Margin | B53: Allcargo | C53: 3.3179 | D53: 2.9146 | E53: 1.5787 | F53: 4.2568 | G53: 3.6258
B54: BlueDart | C54: 2.8437 | D54: -1.3089 | E54: 3.0963 | F54: 8.5839 | G54: 6.9339
B55: Delhivery | C55: -107.8244 | D55: -9.6716 | E55: -11.4011 | F55: -14.8904 | G55: -14.0834
A56: Inferences: | B56: 1. A stable net profit margin for Allcargo Logistics over a five-year period suggests that the company has been able to maintain consistent profitability relative to its revenue.
B57: 2. Negetive Profit margin for Delhivery is indicative that it might have incurred losses
C58: FY 2019 | D58: FY 2020 | E58: FY 2021 | F58: FY 2022 | G58: FY 2023
A59: ROE(%) | B59: Allcargo | C59: =roundup('Horizontal Analysis - Allcargo'!C50/'Horizontal Analysis - Allcargo'!C148*100,3) -> 11.306 | D59: =roundup('Horizontal Analysis - Allcargo'!D50/'Horizontal Analysis - Allcargo'!D148*100,3) -> 9.847 | E59: =roundup('Horizontal Analysis - Allcargo'!E50/'Horizontal Analysis - Allcargo'!E148*100,3) -> 6.333 | F59: =roundup('Horizontal Analysis - Allcargo'!F50/'Horizontal Analysis - Allcargo'!F148*100,3) -> 22.887 | G59: =roundup('Horizontal Analysis - Allcargo'!G50/'Horizontal Analysis - Allcargo'!G148*100,3) -> 21.017
B60: BlueDart | C60: =roundup('IS - BlueDart'!C44/'BS - BlueDart'!C81*100,3) -> 15.626 | D60: =roundup('IS - BlueDart'!D44/'BS - BlueDart'!D81*100,3) -> -8.468 | E60: =roundup('IS - BlueDart'!E44/'BS - BlueDart'!E81*100,3) -> 17.199 | F60: =roundup('IS - BlueDart'!F44/'BS - BlueDart'!F81*100,3) -> 43.417 | G60: =roundup('IS - BlueDart'!G44/'BS - BlueDart'!G81*100,3) -> 30.405
B61: Delhivery | C61: =ROUNDUP('IS - Delhivery'!B35/'BS - Delhivery'!B61*100, 3) -> -52.632 | D61: =ROUNDUP('IS - Delhivery'!C35/'BS - Delhivery'!C61*100, 3) -> -8.483 | E61: =ROUNDUP('IS - Delhivery'!D35/'BS - Delhivery'!D61*100, 3) -> -14.656 | F61: =ROUNDUP('IS - Delhivery'!E35/'BS - Delhivery'!E61*100, 3) -> -17.203 | G61: =ROUNDUP('IS - Delhivery'!F35/'BS - Delhivery'!F61*100, 3) -> -11.089
A62: Inferences: | B62: 1. Allcargo Logistics has been offering a stable ROE over the past 5 years indicative of the fact that it is a good security to invest in

Sheet Dupont Analysis
A1: ROE = (Net Income/Sales)x(sales/Total Assets)x(Total Assets/Equity)
A3: ROE = (Profitability)x(Efficiency)x(Equity Multiplier)
A5: Dupont Analysis for FY 2023
B6: Profitability | C6: Efficiency | D6: Equity Multiplier | F6: ROE
A7: Allcargo logistics | B7: =roundup('Horizontal Analysis - Allcargo'!C50/'Horizontal Analysis - Allcargo'!C6,3) -> 0.034 | C7: ='Ratio Analysis '!G31 -> 3.715 | D7: =roundup('Horizontal Analysis - Allcargo'!C107/'Horizontal Analysis - Allcargo'!C148,3) -> 1.94 | F7: =B7*C7*D7*100 -> 24.50414
A8: BlueDart | B8: =roundup('IS - BlueDart'!C44/'IS - BlueDart'!C4,3) -> 0.029 | C8: ='Ratio Analysis '!G32 -> 1.71 | D8: =roundup('BS - BlueDart'!C38/'BS - BlueDart'!C81,3) -> 3.136 | F8: =B8*C8*D8*100 -> 15.551424
A9: Delhivery | B9: =roundup('IS - Delhivery'!C35/'IS - Delhivery'!C4,3) -> -0.097 | C9: ='Ratio Analysis '!G33 -> 0.744 | D9: =roundup('BS - Delhivery'!B31/'BS - Delhivery'!B61,3) -> 1.199 | F9: =B9*C9*D9*100 -> -8.6529432
A11: Inferences:
B12: 1. The ROE calculated from the dupon analysis is 24.50 for Allcargo which is almost close to calculated by raw calculation from financial statements i.e. 21.017
B13: 2. This shows the accuracy of the method

Sheet IS - BlueDart
A1: In Millions of INR except Per Share | B1: FY 2018 | C1: FY 2019 | D1: FY 2020 | E1: FY 2021 | F1: FY 2022 | G1: FY 2023
A2: 12 Months Ending | B2: 03/31/2018 | C2: 03/31/2019 | D2: 03/31/2020 | E2: 03/31/2021 | F2: 03/31/2022 | G2: 03/31/2023
A3: Revenue | B3: 27992.4 | C3: 31744 | D3: 31751.3 | E3: 32881.3 | F3: 44104.9 | G3: 51722.2
A4: + Sales & Services Revenue | B4: 27992.4 | C4: 31744 | D4: 31751.3 | E4: 32881.3 | F4: 44104.9 | G4: 51722.2
A5: Gross Profit | B5: — | C5: — | D5: — | E5: — | F5: — | G5: —
A6: + Other Operating Income | B6: 74.6 | C6: 73.9 | D6: 55.3 | E6: 127.3 | F6: 307.9 | G6: 0
A7: - Operating Expenses | B7: 25617.5 | C7: 30161.1 | D7: 30478.5 | E7: 30318.4 | F7: 38046.7 | G7: 46290.9
A8: + Selling & Marketing | B8: 21.3 | C8: 16 | D8: 20.2 | E8: 68.3 | F8: 93.2 | G8: 91.7
A9: + Research & Development | B9: 0 | C9: 0 | D9: 0 | E9: — | F9: — | G9: 0
A10: + Depreciation & Amortization | B10: 1144.5 | C10: 1278.9 | D10: 3473.3 | E10: 4300 | F10: 3953.7 | G10: 3944.8
A11: + Prov For Doubtful Accts | B11: — | C11: — | D11: — | E11: — | F11: — | G11: 34.8
A12: + Other Operating Expense | B12: 24451.7 | C12: 28866.2 | D12: 26985 | E12: 25950.1 | F12: 33999.8 | G12: 42219.6
A13: Operating Income (Loss) | B13: 2449.5 | C13: 1656.8 | D13: 1328.1 | E13: 2690.2 | F13: 6366.1 | G13: 5431.3
A14: - Non-Operating (Income) Loss | B14: 272.9 | C14: 308.1 | D14: 1715 | E14: 1292.3 | F14: 1294.9 | G14: 519.2
A15: + Interest Expense, Net | B15: 309.1 | C15: 350.8 | D15: 1104.9 | E15: 1033.8 | F15: 798.9 | G15: 643.5
A16: + Interest Expense | B16: 405 | C16: 426.6 | D16: 1173.8 | E16: 1109.5 | F16: 869.7 | G16: 668.5
A17: - Interest Income | B17: 95.9 | C17: 75.8 | D17: 68.9 | E17: 75.7 | F17: 70.8 | G17: 25
A18: + Other Investment (Inc) Loss | B18: -35.4 | C18: -33.8 | D18: -30.5 | E18: 0 | F18: 0 | G18: —
A19: + Foreign Exch (Gain) Loss | B19: -0.8 | C19: -8.9 | D19: -0.5 | E19: 0 | F19: 0 | G19: 0
A20: + (Income) Loss from Affiliates | B20: — | C20: — | D20: — | E20: — | F20: 0 | G20: —
A21: + Other Non-Op (Income) Loss | B21: 0 | C21: 0 | D21: 641.1 | E21: 258.5 | F21: 496 | G21: -124.3
A22: Pretax Income (Loss), Adjusted | B22: 2176.6 | C22: 1348.7 | D22: -386.9 | E22: 1397.9 | F22: 5071.2 | G22: 4912.1
A23: - Abnormal Losses (Gains) | B23: 6.6 | C23: 7.3 | D23: 4.3 | E23: 0 | F23: -51.7 | G23: -169.9
A24: + Disposal of Assets | B24: 6.6 | C24: 7.3 | D24: 4.3 | E24: — | F24: 1.1 | G24: -0.6
A25: + Asset Write-Down | B25: — | C25: — | D25: — | E25: — | F25: 11.8 | G25: —
A26: + Sale of Investments | B26: — | C26: — | D26: — | E26: — | F26: -64.6 | G26: -169.3
A27: Pretax Income (Loss), GAAP | B27: 2170 | C27: 1341.4 | D27: -391.2 | E27: 1397.9 | F27: 5122.9 | G27: 5082
A28: - Income Tax Expense (Benefit) | B28: 722.9 | C28: 443.8 | D28: 27.4 | E28: 379.8 | F28: 1300.8 | G28: 1376.7
A29: + Current Income Tax | B29: 796.5 | C29: 527.3 | D29: 128.3 | E29: 540.2 | F29: 1373.5 | G29: 1471.3
A30: + Deferred Income Tax | B30: -73.6 | C30: -83.5 | D30: -100.9 | E30: -160.4 | F30: -72.7 | G30: -94.6
A31: + Tax Allowance/Credit | B31: — | C31: — | D31: — | E31: — | F31: — | G31: —
A32: - (Income) Loss from Affiliates | B32: — | C32: — | D32: — | E32: 0 | F32: 0 | G32: —
A33: Income (Loss) from Cont Ops | B33: 1447.1 | C33: 897.6 | D33: -418.6 | E33: 1018.1 | F33: 3822.1 | G33: 3705.3
A34: - Net Extraordinary Losses (Gains) | B34: 0 | C34: 0 | D34: 0 | E34: 0 | F34: 0 | G34: 0
A35: + Discontinued Operations | B35: 0 | C35: 0 | D35: 0 | E35: 0 | F35: 0 | G35: 0
A36: + XO & Accounting Changes | B36: 0 | C36: 0 | D36: 0 | E36: 0 | F36: 0 | G36: 0
A37: Income (Loss) Incl. MI | B37: 1447.1 | C37: 897.6 | D37: -418.6 | E37: 1018.1 | F37: 3822.1 | G37: 3705.3
A38: - Minority Interest | B38: 0 | C38: 0 | D38: 0 | E38: 0 | F38: 0 | G38: 0
A39: Net Income, GAAP | B39: 1447.1 | C39: 897.6 | D39: -418.6 | E39: 1018.1 | F39: 3822.1 | G39: 3705.3
A40: - Preferred Dividends | B40: 0 | C40: 0 | D40: 0 | E40: 0 | F40: 0 | G40: 0
A41: - Other Adjustments | B41: 0 | C41: 0 | D41: 0 | E41: 0 | F41: 0 | G41: 0
A42: Net Income Avail to Common, GAAP | B42: 1447.1 | C42: 897.6 | D42: -418.6 | E42: 1018.1 | F42: 3822.1 | G42: 3705.3
A44: Net Income Avail to Common, Adj | B44: 1451.72 | C44: 902.71 | D44: -415.59 | E44: 1018.1 | F44: 3785.91 | G44: 3586.37
A45: Net Abnormal Losses (Gains) | B45: 4.62 | C45: 5.11 | D45: 3.01 | E45: 0 | F45: -36.19 | G45: -118.93
... A56: Diluted EPS from Cont Ops, Adjusted | B56: 61.1819 | C56: 38.0442 | D56: -17.5148 | E56: 42.91 | F56: 159.555 | G56: 151.1455
A58: Reference Items
A59: Accounting Standard | B59: IN GAAP | C59: IN GAAP | D59: IN GAAP | E59: IN GAAP | F59: IN GAAP | G59: IN GAAP
A60: EBITDA | B60: 3594 | C60: 2935.7 | D60: 4951.3 | E60: 6990.2 | F60: 10319.8 | G60: 9376.1
A61: EBITDA Margin (T12M) | B61: 12.8392 | C61: 9.248 | D61: 15.594 | E61: 21.2589 | F61: 23.3983 | G61: 18.1278
A62: EBITA | B62: 2619.2 | C62: 1831.1 | D62: 1744.4 | E62: 2948.6 | F62: 8796.2 | G62: 5632.4
A63: EBIT | B63: 2449.5 | C63: 1656.8 | D63: 1328.1 | E63: 2690.2 | F63: 6366.1 | G63: 5431.3
A64: Gross Margin | B64: — | C64: — | D64: — | E64: — | F64: — | G64: —
A65: Operating Margin | B65: 8.7506 | C65: 5.2193 | D65: 4.1828 | E65: 8.1815 | F65: 14.434 | G65: 10.5009
A66: Profit Margin | B66: 5.1861 | C66: 2.8437 | D66: -1.3089 | E66: 3.0963 | F66: 8.5839 | G66: 6.9339
A67: Sales per Employee | B67: 2450958.8 | C67: 2373738.1 | D67: 2586242.6 | E67: 3008628.4 | F67: 3589266 | G67: 4106892.2
A68: Dividends per Share | B68: 12.5 | C68: 12.5 | D68: 0 | E68: 15 | F68: 60 | G68: 30
A69: Total Cash Common Dividends | B69: 296.6 | C69: 296.6 | D69: 0 | E69: 355.919 | F69: 830.5 | G69: 711.838
A70: Capitalized Interest Expense | B70: 0 | C70: 0 | D70: — | E70: — | F70: — | G70: —
A71: Personnel Expenses | B71: 5845 | C71: 6983.6 | D71: 7335.3 | E71: 7290.3 | F71: 7654.3 | G71: 8378.2
A72: Export Sales | B72: — | C72: — | D72: — | E72: — | F72: — | G72: —
A73: Depreciation Expense | B73: 974.8 | C73: 1104.6 | D73: 3206.9 | E73: 4041.6 | F73: 1523.6 | G73: 3743.7
A74: Rental Expense | B74: 2605.9 | C74: 2905.2 | D74: 677.9 | E74: 277.8 | F74: 402.5 | G74: 520.1

Sheet BS - BlueDart
A1: In Millions of INR except Per Share | B1: FY 2018 | C1: FY 2019 | D1: FY 2020 | E1: FY 2021 | F1: FY 2022 | G1: FY 2023
A2: 12 Months Ending | B2: 03/31/2018 | C2: 03/31/2019 | D2: 03/31/2020 | E2: 03/31/2021 | F2: 03/31/2022 | G2: 03/31/2023
A3: Total Assets
A4: + Cash, Cash Equivalents & STI | B4: 2278.7 | C4: 2687.1 | D4: 1000 | E4: 4605.9 | F4: 3917.2 | G4: 2664.1
A5: + Cash & Cash Equivalents | B5: 2278.7 | C5: 2687.1 | D5: 1000 | E5: 3105.2 | F5: 1843.3 | G5: 955.2
A6: + ST Investments | B6: 0 | C6: 0 | D6: 0 | E6: 1500.7 | F6: 2073.9 | G6: 1708.9
A7: + Accounts & Notes Receiv | B7: 4222.5 | C7: 4910.2 | D7: 5282.3 | E7: 5179.2 | F7: 5800.1 | G7: 6366.6
A8: + Accounts Receivable, Net | B8: 4222.5 | C8: 4910.2 | D8: 5282.3 | E8: 5179.2 | F8: 5800.1 | G8: 6366.6
A9: + Notes Receivable, Net | B9: 0 | C9: 0 | D9: 0 | E9: 0 | F9: 0 | G9: 0
A10: + Inventories | B10: 213.3 | C10: 260.1 | D10: 269.9 | E10: 317.8 | F10: 349.9 | G10: 393.5
A11: + Raw Materials | B11: 44.8 | C11: 58.9 | D11: 37.3 | E11: 58.2 | F11: 70.1 | G11: 78.4
A12: + Work In Process | B12: 0 | C12: 0 | D12: 0 | E12: 0 | F12: 0 | G12: 0
A13: + Finished Goods | B13: 0 | C13: 0 | D13: 0 | E13: 0 | F13: 0 | G13: 0
A14: + Other Inventory | B14: 168.5 | C14: 201.2 | D14: 232.6 | E14: 259.6 | F14: 279.8 | G14: 315.1
A15: + Other ST Assets | B15: 683.6 | C15: 774.2 | D15: 660.9 | E15: 700.9 | F15: 696 | G15: 1179.3
... A17: + Derivative & Hedging Assets | B17: 0 | C17: 0 | D17: 0 | E17: 0 | F17: 0 | G17: 0
A18: + Assets Held-for-Sale | B18: — | C18: — | D18: — | E18: — | F18: — | G18: —
A19: + Misc ST Assets | B19: 473 | C19: 470.4 | D19: 493.5 | E19: 504.5 | F19: 512.7 | G19: 756.1
A20: Total Current Assets | B20: 7398.1 | C20: 8631.6 | D20: 7213.1 | E20: 10803.8 | F20: 10763.2 | G20: 10603.5
A21: + Property, Plant & Equip, Net | B21: 5241.6 | C21: 6411.6 | D21: 15840.5 | E21: 15111.6 | F21: 14247 | G21: 18029.7
A22: + Property, Plant & Equip | B22: 7549.3 | C22: 9457.2 | D22: 20091.1 | E22: 20661.9 | F22: 25656.3 | G22: 32033.6
A23: - Accumulated Depreciation | B23: 2307.7 | C23: 3045.6 | D23: 4250.6 | E23: 5550.3 | F23: 11409.3 | G23: 14003.9
A24: + LT Investments & Receivables | B24: 0 | C24: 0 | D24: 0 | E24: 0 | F24: 0 | G24: 0
A25: + LT Investments | B25: 0 | C25: 0 | D25: 0 | E25: — | F25: 0 | G25: 0
A26: + LT Marketable Securities | B26: — | C26: — | D26: — | E26: — | F26: — | G26: 0
A27: + LT Receivables | B27: — | C27: — | D27: — | E27: 0 | F27: — | G27: —
A28: + Other LT Assets | B28: 2385.8 | C28: 3069.4 | D28: 3354.3 | E28: 3058.9 | F28: 3277.4 | G28: 3597.2
A29: + Total Intangible Assets | B29: 933.6 | C29: 1038.6 | D29: 989.6 | E29: 787 | F29: 813 | G29: 729.7
A30: + Goodwill | B30: 0 | C30: 0 | D30: 0 | E30: 0 | F30: 0 | G30: 0
A31: + Other Intangible Assets | B31: 933.6 | C31: 1038.6 | D31: 989.6 | E31: 787 | F31: 813 | G31: 729.7
A32: + Prepaid Expense | B32: 179.1 | C32: 122.3 | D32: 30.2 | E32: 60.3 | F32: 51.2 | G32: 114.1
A33: + Deferred Tax Assets | B33: 386.5 | C33: 513.2 | D33: 645.1 | E33: 807.8 | F33: 905.6 | G33: 1023.8
A34: + Derivative & Hedging Assets | B34: 0 | C34: 0 | D34: 0 | E34: 0 | F34: 0 | G34: 0
A35: + Investments in Affiliates | B35: — | C35: — | D35: — | E35: 0 | F35: 0 | G35: —
A36: + Misc LT Assets | B36: 886.6 | C36: 1395.3 | D36: 1689.4 | E36: 1403.8 | F36: 1507.6 | G36: 1729.6
A37: Total Noncurrent Assets | B37: 7627.4 | C37: 9481 | D37: 19194.8 | E37: 18170.5 | F37: 17524.4 | G37: 21626.9
A38: Total Assets | B38: 15025.5 | C38: 18112.6 | D38: 26407.9 | E38: 28974.3 | F38: 28287.6 | G38: 32230.4
A40: Liabilities & Shareholders' Equity
A41: + Payables & Accruals | B41: 5028.1 | C41: 6038.5 | D41: 6179.9 | E41: 7159.5 | F41: 8158.4 | G41: 7180.6
A42: + Accounts Payable | B42: 2759 | C42: 4342.5 | D42: 4010.3 | E42: 5094.1 | F42: 5798.7 | G42: 5851
A43: + Accrued Taxes | B43: — | C43: — | D43: — | E43: — | F43: — | G43: —
A44: + Interest & Dividends Payable | B44: 12.7 | C44: 11 | D44: 15.6 | E44: 5.9 | F44: 33.4 | G44: 5.4
A45: + Other Payables & Accruals | B45: 2256.4 | C45: 1685 | D45: 2154 | E45: 2059.5 | F45: 2326.3 | G45: 1324.2
A46: + ST Debt | B46: 974.3 | C46: 711.8 | D46: 1623.6 | E46: 1786.7 | F46: 4009.8 | G46: 2105.1
A47: + ST Borrowings | B47: 974.3 | C47: 711.8 | D47: 0 | E47: 0 | F47: 2000 | G47: 0
A48: + ST Lease Liabilities | B48: 0 | C48: 0 | D48: 1623.6 | E48: 1786.7 | F48: 2009.8 | G48: 2105.1
A49: + ST Finance Leases | B49: 0 | C49: 0 | D49: — | E49: — | F49: — | G49: —
A50: + Other ST Liabilities | B50: 411.6 | C50: 1116.2 | D50: 1631.6 | E50: 3959.5 | F50: 559.6 | G50: 1872.9
A51: + Deferred Revenue | B51: 0 | C51: 0 | D51: 0 | E51: 0 | F51: 0 | G51: 0
A52: + Derivatives & Hedging | B52: 0 | C52: 0 | D52: 0 | E52: 0 | F52: 0 | G52: 0
A53: + Deferred Tax Liabilities | B53: — | C53: — | D53: — | E53: 0 | F53: 0 | G53: —
A54: + Misc ST Liabilities | B54: 411.6 | C54: 1116.2 | D54: 1631.6 | E54: 3959.5 | F54: 559.6 | G54: 1872.9
A55: Total Current Liabilities | B55: 6414 | C55: 7866.5 | D55: 9435.1 | E55: 12905.7 | F55: 12727.8 | G55: 11158.6
A56: + LT Debt | B56: 3086.8 | C56: 4250 | D56: 11785.6 | E56: 9934.8 | F56: 6649.6 | G56: 9096.3
A57: + LT Borrowings | B57: 3086.8 | C57: 4250 | D57: 4100 | E57: 2450 | F57: 0 | G57: 2500
A58: + LT Lease Liabilities | B58: 0 | C58: 0 | D58: 7685.6 | E58: 7484.8 | F58: 6649.6 | G58: 6596.3
A59: + LT Finance Leases | B59: 0 | C59: 0 | D59: — | E59: — | F59: — | G59: —
A60: + Other LT Liabilities | B60: 206.6 | C60: 218.9 | D60: 278.9 | E60: 214.2 | F60: 190.3 | G60: 179.9
A61: + Accrued Liabilities | B61: 0 | C61: 0 | D61: 0 | E61: 0 | F61: 0 | G61: 0
A62: + Pension Liabilities | B62: 0 | C62: 0 | D62: 0 | E62: 0 | F62: 0 | G62: 0
A63: + Pensions | B63: 0 | C63: 0 | D63: 0 | E63: 0 | F63: 0 | G63: 0
A64: + Other Post-Ret Benefits | B64: 0 | C64: 0 | D64: 0 | E64: 0 | F64: 0 | G64: 0
A65: + Deferred Compensation | B65: 83.2 | C65: 116.8 | D65: 179.6 | E65: 156.4 | F65: 165.8 | G65: 152.4
A66: + Deferred Revenue | B66: 0 | C66: 0 | D66: 0 | E66: 0 | F66: 0 | G66: 0
A67: + Deferred Tax Liabilities | B67: 0 | C67: 0 | D67: 0 | E67: 0 | F67: 0 | G67: —
A68: + Derivatives & Hedging | B68: 0 | C68: 0 | D68: 0 | E68: 0 | F68: 0 | G68: 0
A69: + Misc LT Liabilities | B69: 123.4 | C69: 102.1 | D69: 99.3 | E69: 57.8 | F69: 24.5 | G69: 27.5
A70: Total Noncurrent Liabilities | B70: 3293.4 | C70: 4468.9 | D70: 12064.5 | E70: 10149 | F70: 6839.9 | G70: 9276.2
A71: Total Liabilities | B71: 9707.4 | C71: 12335.4 | D71: 21499.6 | E71: 23054.7 | F71: 19567.7 | G71: 20434.8
A72: + Preferred Equity and Hybrid Capital | B72: 0 | C72: 0 | D72: 0 | E72: 0 | F72: 0 | G72: 0
A73: + Share Capital & APIC | B73: 585.1 | C73: 585.1 | D73: 585.1 | E73: 585.1 | F73: 585.1 | G73: 585.1
A74: + Common Stock | B74: 237.6 | C74: 237.6 | D74: 237.6 | E74: 237.6 | F74: 237.6 | G74: 237.6
A75: + Additional Paid in Capital | B75: 347.5 | C75: 347.5 | D75: 347.5 | E75: 347.5 | F75: 347.5 | G75: 347.5
A76: - Treasury Stock | B76: 0 | C76: 0 | D76: 0 | E76: 0 | F76: 0 | G76: 0
A77: + Retained Earnings | B77: 3781.4 | C77: 4407.6 | D77: 3695.9 | E77: 4707.2 | F77: 7505.2 | G77: 10577
A78: + Other Equity | B78: 951.6 | C78: 784.5 | D78: 627.3 | E78: 627.3 | F78: 629.6 | G78: 633.5
A79: Equity Before Minority Interest | B79: 5318.1 | C79: 5777.2 | D79: 4908.3 | E79: 5919.6 | F79: 8719.9 | G79: 11795.6
... A82: Total Liabilities & Equity | B82: 15025.5 | C82: 18112.6 | D82: 26407.9 | E82: 28974.3 | F82: 28287.6 | G82: 32230.4
A84: Reference Items
A85: Accounting Standard | B85: IN GAAP | C85: IN GAAP | D85: IN GAAP | E85: IN GAAP | F85: IN GAAP | G85: IN GAAP
A86: Shares Outstanding | B86: 23.7279 | C86: 23.7279 | D86: 23.7279 | E86: 23.7279 | F86: 23.7279 | G86: 23.7279
A87: Number of Treasury Shares | B87: 0 | C87: 0 | D87: 0 | E87: 0 | F87: 0 | G87: 0
A88: Pension Obligations | B88: 0 | C88: 0 | D88: 0 | E88: 0 | F88: 165.8 | G88: 0
A89: Future Minimum Operating Lease Obligations | B89: 9530 | C89: 7738.9 | D89: — | E89: — | F89: — | G89: —
A90: Capital Leases - Total | B90: 0 | C90: 0 | D90: — | E90: — | F90: — | G90: —
A91: Percent Of Foreign Ownership | B91: 6.85 | C91: 4.67 | D91: 2.84 | E91: 2.21 | F91: 3.56 | G91: —
A92: Number Of Shareholders | B92: 17192 | C92: 17438 | D92: 17299 | E92: 22702 | F92: 30367 | G92: 37562
A93: Options Granted During Period | B93: 0 | C93: 0 | D93: 0 | E93: — | F93: — | G93: 0.0105
A94: Options Outstanding at Period End | B94: 0 | C94: 0 | D94: 0 | E94: — | F94: — | G94: 0.0163
A95: Net Debt | B95: 1782.4 | C95: 2274.7 | D95: 12409.2 | E95: 7115.6 | F95: 6742.2 | G95: 8537.3
A96: Net Debt to Equity | B96: 33.5157 | C96: 39.3737 | D96: 252.8207 | E96: 120.2041 | F96: 77.3197 | G96: 72.377
A97: Tangible Common Equity Ratio | B97: 31.1136 | C97: 27.7533 | D97: 15.4168 | E97: 18.2089 | F97: 28.7789 | G97: 35.1291
A98: Current Ratio | B98: 1.1534 | C98: 1.0973 | D98: 0.7645 | E98: 0.8371 | F98: 0.8456 | G98: 0.9503
A99: Number of Employees | B99: 11421 | C99: 13373 | D99: 12277 | E99: 10929 | F99: 12288 | G99: 12594

Sheet IS - Delhivery
A1: In Millions of INR except Per Share | B1: FY 2019 | C1: FY 2020 | D1: FY 2021 | E1: FY 2022 | F1: FY 2023
A2: 12 Months Ending | B2: 03/31/2019 | C2: 03/31/2020 | D2: 03/31/2021 | E2: 03/31/2022 | F2: 03/31/2023
A3: Revenue | B3: 16538.97 | C3: 27805.75 | D3: 36465.27 | E3: 68822.86 | F3: 72253.01
A4: + Sales & Services Revenue | B4: 16538.97 | C4: 27805.75 | D4: 36465.27 | E4: 68822.86 | F4: 72253.01
A5: Gross Profit | B5: — | C5: — | D5: — | E5: — | F5: —
A6: - Operating Expenses | B6: 34423.65 | C6: 32082.13 | D6: 41240.77 | E6: 79847.18 | F6: 85220.35
A7: + Depreciation & Amortization | B7: 1700.05 | C7: 2555.91 | D7: 3546.2 | E7: 6107.47 | F7: 8311.44
A8: + Other Operating Expense | B8: 32723.6 | C8: 29526.22 | D8: 37694.57 | E8: 73739.71 | F8: 76908.91
A9: Operating Income (Loss) | B9: -17884.68 | C9: -4276.38 | D9: -4775.5 | E9: -11024.32 | F9: -12967.34
A10: - Non-Operating (Income) Loss | B10: -51.64 | C10: -1588.36 | D10: -618.07 | E10: -533.85 | F10: -2296.92
A11: + Interest Expense, Net | B11: — | C11: 492.18 | D11: 886.27 | E11: — | F11: —
A12: + Interest Expense | B12: 358.13 | C12: 492.18 | D12: 886.27 | E12: — | F12: —
A13: - Interest Income | B13: — | C13: 0 | D13: 0 | E13: — | F13: —
A14: + Foreign Exch (Gain) Loss | B14: 0 | C14: 0 | D14: 0 | E14: 0 | F14: 0
A15: + (Income) Loss from Affiliates | B15: — | C15: — | D15: — | E15: 32.27 | F15: -135.74
A16: + Other Non-Op (Income) Loss | B16: -409.77 | C16: -2080.54 | D16: -1504.34 | E16: -566.12 | F16: -2161.18
A17: Pretax Income (Loss), Adjusted | B17: -17833.04 | C17: -2688.02 | D17: -4157.43 | E17: -10490.47 | F17: -10670.42
A18: - Abnormal Losses (Gains) | B18: 0 | C18: 0 | D18: 0 | E18: -197.17 | F18: -139.82
A19: + Disposal of Assets | B19: — | C19: — | D19: — | E19: -0.08 | F19: —
A20: + Sale of Investments | B20: — | C20: — | D20: — | E20: -197.09 | F20: -139.82
A21: Pretax Income (Loss), GAAP | B21: -17833.04 | C21: -2688.02 | D21: -4157.43 | E21: -10293.3 | F21: -10530.6
A22: - Income Tax Expense (Benefit) | B22: 0 | C22: 1.24 | D22: 0 | E22: -183.3 | F22: -452.81
A23: + Current Income Tax | B23: 0 | C23: 1.24 | D23: 0 | E23: 100.72 | F23: 107.38
A24: + Deferred Income Tax | B24: 0 | C24: 0 | D24: 0 | E24: -284.02 | F24: -560.19
A25: Income (Loss) from Cont Ops | B25: -17833.04 | C25: -2689.26 | D25: -4157.43 | E25: -10110 | F25: -10077.79
A26: - Net Extraordinary Losses (Gains) | B26: 0 | C26: 0 | D26: 0 | E26: 0 | F26: 0
A27: + Discontinued Operations | B27: 0 | C27: 0 | D27: 0 | E27: 0 | F27: 0
A28: + XO & Accounting Changes | B28: 0 | C28: 0 | D28: 0 | E28: 0 | F28: 0
A29: Income (Loss) Incl. MI | B29: -17833.04 | C29: -2689.26 | D29: -4157.43 | E29: -10110 | F29: -10077.79
A30: Net Income, GAAP | B30: -17833.04 | C30: -2689.26 | D30: -4157.43 | E30: -10110 | F30: -10077.79
A31: - Preferred Dividends | B31: — | C31: — | D31: — | E31: 0 | F31: 0
A32: - Other Adjustments | B32: — | C32: 0 | D32: 0 | E32: 0 | F32: 0
A33: Net Income Avail to Common, GAAP | B33: -17833.04 | C33: -2689.26 | D33: -4157.43 | E33: -10110 | F33: -10077.79
A35: Net Income Avail to Common, Adj | B35: -17833.04 | C35: -2689.26 | D35: -4157.43 | E35: -10248.019 | F35: -10175.664
A36: Net Abnormal Losses (Gains) | B36: 0 | C36: 0 | D36: 0 | E36: -138.019 | F36: -97.874
A37: Net Extraordinary Losses (Gains) | B37: 0 | C37: 0 | D37: 0 | E37: 0 | F37: 0
A39: Basic Weighted Avg Shares | B39: — | C39: — | D39: — | E39: 642.11 | F39: 715.16
A40: Basic EPS, GAAP | B40: — | C40: — | D40: -8.05 | E40: -15.745 | F40: -14.09
A41: Basic EPS from Cont Ops, GAAP | B41: — | C41: — | D41: -8.05 | E41: -15.745 | F41: -14.09
A42: Basic EPS from Cont Ops, Adjusted | B42: — | C42: — | D42: -8.05 | E42: -15.9599 | F42: -14.2285
A44: Diluted Weighted Avg Shares | B44: — | C44: — | D44: — | E44: 642.11 | F44: 715.16
A45: Diluted EPS, GAAP | B45: — | C45: — | D45: -8.05 | E45: -15.745 | F45: -14.09
A46: Diluted EPS from Cont Ops, GAAP | B46: — | C46: — | D46: -8.05 | E46: -15.745 | F46: -14.09
A47: Diluted EPS from Cont Ops, Adjusted | B47: — | C47: — | D47: -8.05 | E47: -15.9599 | F47: -14.2285
A49: Reference Items
A50: Accounting Standard | B50: IN GAAP | C50: IN GAAP | D50: IN GAAP | E50: IN GAAP | F50: IN GAAP
A51: EBITDA | B51: -16184.63 | C51: -1720.51 | D51: -1229.3 | E51: -7349.97 | F51: -4655.9
A52: EBITDA Margin (T12M) | B52: -97.8575 | C52: -6.1876 | D52: -3.3712 | E52: -10.6795 | F52: -6.4439
A53: EBITA | B53: -17846.67 | C53: -4192.62 | D53: -4698.94 | E53: -9687.17 | F53: -10663.91
A54: EBIT | B54: -17884.68 | C54: -4276.38 | D54: -4775.5 | E54: -11024.32 | F54: -12967.34
A55: Gross Margin | B55: — | C55: — | D55: — | E55: — | F55: —
A56: Operating Margin | B56: -108.1366 | C56: -15.3795 | D56: -13.096 | E56: -16.0184 | F56: -17.9471
A57: Profit Margin | B57: -107.8244 | C57: -9.6716 | D57: -11.4011 | E57: -14.8904 | F57: -14.0834
A58: Current Profit | B58: — | C58: — | D58: — | E58: — | F58: —
A59: Dividends per Share | B59: 0 | C59: 0 | D59: 0 | E59: 0 | F59: 0
A60: Total Cash Common Dividends | B60: 0 | C60: 0 | D60: 0 | E60: 0 | F60: 0
A61: Personnel Expenses | B61: 3446.39 | C61: 4908.94 | D61: 6109.23 | E61: 13132.65 | F61: 14000.34
A62: Depreciation Expense | B62: 1662.04 | C62: 2472.11 | D62: 3469.64 | E62: 2337.2 | F62: 6008.01

Sheet BS - Delhivery
A1: In Millions of INR except Per Share | B1: FY 2019 | C1: FY 2020 | D1: FY 2021 | E1: FY 2022 | F1: FY 2023
A2: 12 Months Ending | B2: 03/31/2019 | C2: 03/31/2020 | D2: 03/31/2021 | E2: 03/31/2022 | F2: 03/31/2023
A3: Total Assets
A4: + Cash, Cash Equivalents & STI | B4: 27938.59 | C4: 12191.41 | D4: 9850.05 | E4: 16902.33 | F4: 21271.72
A5: + Cash & Cash Equivalents | B5: 16634.32 | C5: 4087 | D5: 2774.41 | E5: 2290 | F5: 6454.52
A6: + ST Investments | B6: 11304.27 | C6: 8104.41 | D6: 7075.64 | E6: 14612.33 | F6: 14817.2
A7: + Accounts & Notes Receiv | B7: 2146.5 | C7: 6013.31 | D7: 5945.82 | E7: 9902.5 | F7: 9436.37
A8: + Accounts Receivable, Net | B8: — | C8: — | D8: — | E8: 9902.5 | F8: 9436.37
A9: + Notes Receivable, Net | B9: — | C9: — | D9: — | E9: 0 | F9: 0
A10: + Inventories | B10: 226.33 | C10: 178.32 | D10: 259.48 | E10: 253.06 | F10: 193.56
A11: + Raw Materials | B11: — | C11: 0 | D11: — | E11: — | F11: —
A12: + Work In Process | B12: — | C12: 0 | D12: — | E12: — | F12: —
A13: + Finished Goods | B13: — | C13: 178.32 | D13: 259.48 | E13: — | F13: —
A14: + Other Inventory | B14: — | C14: 0 | D14: — | E14: — | F14: —
A15: + Other ST Assets | B15: 2384.49 | C15: 7344.54 | D15: 12249.63 | E15: 12541.87 | F15: 38486.93
A16: + Misc ST Assets | B16: 2384.49 | C16: 7344.54 | D16: 12249.63 | E16: 12541.87 | F16: 38486.93
A17: Total Current Assets | B17: 32695.91 | C17: 25727.58 | D17: 28304.98 | E17: 39599.76 | F17: 69388.58
A18: + Property, Plant & Equip, Net | B18: 4594.04 | C18: 7407.27 | D18: 10975.3 | E18: 13750.02 | F18: 14833.43
A19: + Property, Plant & Equip | B19: — | C19: 10693.15 | D19: 15684.94 | E19: — | F19: 24454.52
A20: - Accumulated Depreciation | B20: — | C20: 3285.88 | D20: 4709.64 | E20: — | F20: 9621.09
A21: + LT Investments & Receivables | B21: 274.33 | C21: 3772.39 | D21: 4205.89 | E21: 6295.06 | F21: 6124.67
A22: + LT Investments | B22: 274.33 | C22: 3772.39 | D22: 4205.89 | E22: 6295.06 | F22: 6124.67
A23: + Other LT Assets | B23: 3061.17 | C23: 6665.84 | D23: 2491.81 | E23: 22863.16 | F23: 21546.17
A24: + Total Intangible Assets | B24: 294.42 | C24: 348.29 | D24: 326.03 | E24: 17373.62 | F24: 15347.34
A25: + Goodwill | B25: 163.8 | C25: 186.4 | D25: 186.48 | E25: 13799.04 | F25: 13620.7
A26: + Other Intangible Assets | B26: 130.62 | C26: 161.89 | D26: 139.55 | E26: 3574.58 | F26: 1726.64
A27: + Deferred Tax Assets | B27: 596.45 | C27: 1050.15 | D27: 1231.69 | E27: — | F27: 229.02
A28: + Investments in Affiliates | B28: — | C28: 0 | D28: — | E28: 0 | F28: 0
A29: + Misc LT Assets | B29: 2170.3 | C29: 5267.4 | D29: 934.09 | E29: 5489.54 | F29: 5969.81
A30: Total Noncurrent Assets | B30: 7929.54 | C30: 17845.5 | D30: 17673 | E30: 42908.24 | F30: 42504.27
A31: Total Assets | B31: 40625.45 | C31: 43573.08 | D31: 45977.98 | E31: 82508 | F31: 111892.85
A33: Liabilities & Shareholders' Equity
A34: + Payables & Accruals | B34: 1582.39 | C34: 2733.5 | D34: 4422.3 | E34: 8345 | F34: 7873.55
A35: + Accounts Payable | B35: 0.61 | C35: 7.97 | D35: 20.52 | E35: 8345 | F35: 7873.55
A36: + Other Payables & Accruals | B36: 1581.78 | C36: 2725.53 | D36: 4401.78 | E36: — | F36: —
A37: + ST Debt | B37: 1324.4 | C37: 2677.79 | D37: 3314.5 | E37: 4111.56 | F37: 2747.36
A38: + ST Borrowings | B38: 579.97 | C38: 1570.13 | D38: 1697.34 | E38: 2355.28 | F38: 844.67
A39: + ST Lease Liabilities | B39: 744.43 | C39: 1107.66 | D39: 1617.16 | E39: 1756.28 | F39: 1902.69
A40: + Other ST Liabilities | B40: 920.76 | C40: 1421.84 | D40: 1799.52 | E40: 2562.44 | F40: 2189.9
A41: + Deferred Tax Liabilities | B41: 0 | C41: 1.24 | D41: 1.2 | E41: 0 | F41: 0
A42: + Misc ST Liabilities | B42: 920.76 | C42: 1420.6 | D42: 1798.32 | E42: 2562.44 | F42: 2189.9
A43: Total Current Liabilities | B43: 3827.55 | C43: 6833.13 | D43: 9536.32 | E43: 15019 | F43: 12810.81
A44: + LT Debt | B44: 2781.42 | C44: 4868.67 | D44: 7854.53 | E44: 6903.63 | F44: 6487.07
A45: + LT Borrowings | B45: 356.2 | C45: 998.02 | D45: 1316.09 | E45: 1176.11 | F45: 1144.07
A46: + LT Lease Liabilities | B46: 2425.22 | C46: 3870.65 | D46: 6538.44 | E46: 5727.52 | F46: 5343
A47: + Other LT Liabilities | B47: 133.65 | C47: 167.22 | D47: 219.16 | E47: 1011.68 | F47: 823.6
A48: + Accrued Liabilities | B48: 0 | C48: 0 | D48: 0 | E48: — | F48: —
A49: + Deferred Tax Liabilities | B49: 0 | C49: 0 | D49: 0 | E49: 629.13 | F49: 312.55
A50: + Misc LT Liabilities | B50: 133.65 | C50: 167.22 | D50: 219.16 | E50: 382.55 | F50: 511.05
A51: Total Noncurrent Liabilities | B51: 2915.07 | C51: 5035.89 | D51: 8073.69 | E51: 7915.31 | F51: 7310.67
A52: Total Liabilities | B52: 6742.62 | C52: 11869.02 | D52: 17610.01 | E52: 22934.31 | F52: 20121.48
A53: + Preferred Equity and Hybrid Capital | B53: 391.72 | C53: 391.72 | D53: 353.99 | E53: 0 | F53: 0
A54: + Share Capital & APIC | B54: — | C54: 74079.43 | D54: 74323.19 | E54: — | F54: 154324.61
A55: + Common Stock | B55: 9.58 | C55: 9.75 | D55: 16.33 | E55: 642.11 | F55: 728.72
A56: + Additional Paid in Capital | B56: — | C56: 74069.68 | D56: 74306.86 | E56: — | F56: 153595.89
A57: - Treasury Stock | B57: — | C57: 0 | D57: — | E57: 0 | F57: 0
A58: + Retained Earnings | B58: — | C58: -44132.36 | D58: -48279.41 | E58: — | F58: -68463.37
A59: + Other Equity | B59: 33481.53 | C59: 1365.27 | D59: 1970.2 | E59: 58931.58 | F59: 5910.13
A60: Equity Before Minority Interest | B60: 33882.83 | C60: 31704.06 | D60: 28367.97 | E60: 59573.69 | F60: 91771.37
A61: Total Equity | B61: 33882.83 | C61: 31704.06 | D61: 28367.97 | E61: 59573.69 | F61: 91771.37
A62: Total Liabilities & Equity | B62: 40625.45 | C62: 43573.08 | D62: 45977.98 | E62: 82508 | F62: 111892.85
A64: Reference Items
A65: Accounting Standard | B65: IN GAAP | C65: IN GAAP | D65: IN GAAP | E65: IN GAAP | F65: IN GAAP
A66: Shares Outstanding | B66: — | C66: 0.975 | D66: — | E66: 642.11 | F66: 728.72
A67: Number of Treasury Shares | B67: — | C67: 0 | D67: 0 | E67: 0 | F67: 0
A68: Net Debt | B68: -23832.77 | C68: -4644.95 | D68: 1318.98 | E68: -5887.14 | F68: -12037.29
A69: Net Debt to Equity | B69: -70.3388 | C69: -14.651 | D69: 4.6495 | E69: -9.8821 | F69: -13.1166
A70: Tangible Common Equity Ratio | B70: 82.3105 | C70: 71.6349 | D70: 60.6501 | E70: 64.7892 | F70: 79.1586
A71: Current Ratio | B71: 8.5423 | C71: 3.7651 | D71: 2.9681 | E71: 2.6366 | F71: 5.4164
A72: Cash Conversion Cycle | B72: — | C72: 1175.0993 | D72: 814.1824 | E72: -780.0366 | F72: —
